{"PageElementIdentifier":"2b325173-94b8-4185-96ee-8c81cf6f6ad6","ResourceKey":"THE.fad1b7bf-6bb3-4512-a899-bdc7cfcb7fa5","Type":"THE.Card_Byte","Width":250,"Height":320,"CardName":{"Value":null,"Type":"String"},"CardType":{"Value":"","Type":"Short"},"Safe":{"Value":"","Type":"Boolean"},"Value":{"Value":"","Type":"UInteger"},"I0_00":{"Value":null,"Type":"String"},"I0_01":{"Value":null,"Type":"String"},"I0_02":{"Value":null,"Type":"String"},"I0_03":{"Value":null,"Type":"String"},"I0_04":{"Value":null,"Type":"String"},"I0_05":{"Value":null,"Type":"String"},"I0_06":{"Value":null,"Type":"String"},"I0_07":{"Value":null,"Type":"String"},"IagControls":[{"PageElementIdentifier":"3f89d5dd-0000-43e4-8de9-39e1ee0ea86c","ResourceKey":"Omron.StandardShapes.Rectangle","Name":"R_FormingBackground_SP","Fill":{"c":854782706},"Stroke":{"c":4278190080},"Top":29.999999999999957,"Width":250,"Height":290,"isDefaultProperty":false},{"PageElementIdentifier":"574937ff-bdad-4b2b-a201-7ab79ce799bc","ResourceKey":"Omron.StandardControls.DataDisplay","Name":"D_CardName","FontFamily":"abb64941-8677-48f0-80f4-990e6e67b265","FontSize":"2d85f7f2-a5cf-4af8-b34c-5c10c05b45bb","FontStyle":"d6142689-6e0f-434d-be90-8b77c008373c","HorizontalContentAlignment":{"v":"Left"},"VerticalContentAlignment":{"v":"Center"},"DataType":{"v":"Text"},"Expression":"CardName","Width":250,"Height":30,"isDefaultProperty":false},{"PageElementIdentifier":"9d6c4861-360f-48e5-b5e6-caf453479abd","ResourceKey":"Omron.ControlContainers.Group","Name":"Group0","Left":22,"Top":80,"Width":202.99999999999994,"Height":20,"ChildControls":[{"PageElementIdentifier":"90f40ac0-66ac-432c-aaee-7c3d21b73e68","ResourceKey":"Omron.LampControls.BitLamp","Name":"BL_StateBit0","Design":{"v":"Rectangle"},"FontFamily":"abb64941-8677-48f0-80f4-990e6e67b265","FontSize":"e5a8243f-dccc-4c38-9e0e-cecb2fe15b52","FontStyle":"d6142689-6e0f-434d-be90-8b77c008373c","BackgroundColorOn":{"ColorContext":null,"A":255,"R":255,"G":165,"B":0,"ScA":1,"ScR":1,"ScG":0.376262158,"ScB":0},"BorderBrush":{"c":4278190080},"BorderThickness":{"Left":1,"Top":1,"Right":1,"Bottom":1},"Expression":"Value AND 1","Top":3,"Width":15,"Height":15,"isDefaultProperty":false},{"PageElementIdentifier":"e178e967-cc19-4a8a-899b-ef122948091e","ResourceKey":"Omron.StandardControls.DataDisplay","Name":"D_NameBit0","FontFamily":"abb64941-8677-48f0-80f4-990e6e67b265","FontSize":"e5a8243f-dccc-4c38-9e0e-cecb2fe15b52","FontStyle":"d6142689-6e0f-434d-be90-8b77c008373c","HorizontalContentAlignment":{"v":"Left"},"VerticalContentAlignment":{"v":"Center"},"NAPadding":{"Left":2,"Top":1,"Right":2,"Bottom":2},"Expression":"I0_00","Left":28.000000000000014,"Width":174.99999999999994,"Height":20,"isDefaultProperty":false}],"isDefaultProperty":false},{"PageElementIdentifier":"44cb848b-d778-4375-9880-c4d02187d142","ResourceKey":"Omron.ControlContainers.Group","Name":"Group1","Left":22,"Top":110,"Width":202.99999999999994,"Height":20,"ChildControls":[{"PageElementIdentifier":"ebace9ad-7229-463e-b280-ad8239335a2a","ResourceKey":"Omron.LampControls.BitLamp","Name":"BL_StateBit1","Design":{"v":"Rectangle"},"FontFamily":"abb64941-8677-48f0-80f4-990e6e67b265","FontSize":"e5a8243f-dccc-4c38-9e0e-cecb2fe15b52","FontStyle":"d6142689-6e0f-434d-be90-8b77c008373c","BackgroundColorOn":{"ColorContext":null,"A":255,"R":255,"G":165,"B":0,"ScA":1,"ScR":1,"ScG":0.376262158,"ScB":0},"BorderBrush":{"c":4278190080},"BorderThickness":{"Left":1,"Top":1,"Right":1,"Bottom":1},"Expression":"Value And 2","Top":3,"Width":15,"Height":15,"isDefaultProperty":false},{"PageElementIdentifier":"c22bccd3-042b-41ca-aad9-473bf57dd304","ResourceKey":"Omron.StandardControls.DataDisplay","Name":"D_NameBit1","FontFamily":"abb64941-8677-48f0-80f4-990e6e67b265","FontSize":"e5a8243f-dccc-4c38-9e0e-cecb2fe15b52","FontStyle":"d6142689-6e0f-434d-be90-8b77c008373c","HorizontalContentAlignment":{"v":"Left"},"VerticalContentAlignment":{"v":"Center"},"NAPadding":{"Left":2,"Top":1,"Right":2,"Bottom":2},"Expression":"I0_01","Left":28.000000000000014,"Width":174.99999999999994,"Height":20,"isDefaultProperty":false}],"isDefaultProperty":false},{"PageElementIdentifier":"051d5971-fa43-45d9-84bc-2d1b34760eaa","ResourceKey":"Omron.ControlContainers.Group","Name":"Group2","Left":22,"Top":140,"Width":202.99999999999994,"Height":20,"ChildControls":[{"PageElementIdentifier":"e0798e2f-c0c8-4f6d-9c1f-343f7ef96817","ResourceKey":"Omron.LampControls.BitLamp","Name":"BL_StateBit2","Design":{"v":"Rectangle"},"FontFamily":"abb64941-8677-48f0-80f4-990e6e67b265","FontSize":"e5a8243f-dccc-4c38-9e0e-cecb2fe15b52","FontStyle":"d6142689-6e0f-434d-be90-8b77c008373c","BackgroundColorOn":{"ColorContext":null,"A":255,"R":255,"G":165,"B":0,"ScA":1,"ScR":1,"ScG":0.376262158,"ScB":0},"BorderBrush":{"c":4278190080},"BorderThickness":{"Left":1,"Top":1,"Right":1,"Bottom":1},"Expression":"Value AND 4","Top":3,"Width":15,"Height":15,"isDefaultProperty":false},{"PageElementIdentifier":"2b4f1533-a608-4fdb-a236-ad23c8045a5f","ResourceKey":"Omron.StandardControls.DataDisplay","Name":"D_NameBit2","FontFamily":"abb64941-8677-48f0-80f4-990e6e67b265","FontSize":"e5a8243f-dccc-4c38-9e0e-cecb2fe15b52","FontStyle":"d6142689-6e0f-434d-be90-8b77c008373c","HorizontalContentAlignment":{"v":"Left"},"VerticalContentAlignment":{"v":"Center"},"NAPadding":{"Left":2,"Top":1,"Right":2,"Bottom":2},"Expression":"I0_02","Left":28.000000000000014,"Width":174.99999999999994,"Height":20,"isDefaultProperty":false}],"isDefaultProperty":false},{"PageElementIdentifier":"c1193ed7-babd-42e4-8818-dc277f202780","ResourceKey":"Omron.ControlContainers.Group","Name":"Group3","Left":22,"Top":170,"Width":202.99999999999994,"Height":20,"ChildControls":[{"PageElementIdentifier":"f1f60982-a878-44d1-a712-0827465b823e","ResourceKey":"Omron.LampControls.BitLamp","Name":"BL_StateBit3","Design":{"v":"Rectangle"},"FontFamily":"abb64941-8677-48f0-80f4-990e6e67b265","FontSize":"e5a8243f-dccc-4c38-9e0e-cecb2fe15b52","FontStyle":"d6142689-6e0f-434d-be90-8b77c008373c","BackgroundColorOn":{"ColorContext":null,"A":255,"R":255,"G":165,"B":0,"ScA":1,"ScR":1,"ScG":0.376262158,"ScB":0},"BorderBrush":{"c":4278190080},"BorderThickness":{"Left":1,"Top":1,"Right":1,"Bottom":1},"Expression":"Value And 8","Top":3,"Width":15,"Height":15,"isDefaultProperty":false},{"PageElementIdentifier":"1b4518f9-3364-494f-bcf3-4ac58417eea5","ResourceKey":"Omron.StandardControls.DataDisplay","Name":"D_NameBit3","FontFamily":"abb64941-8677-48f0-80f4-990e6e67b265","FontSize":"e5a8243f-dccc-4c38-9e0e-cecb2fe15b52","FontStyle":"d6142689-6e0f-434d-be90-8b77c008373c","HorizontalContentAlignment":{"v":"Left"},"VerticalContentAlignment":{"v":"Center"},"NAPadding":{"Left":2,"Top":1,"Right":2,"Bottom":2},"Expression":"I0_03","Left":28.000000000000014,"Width":174.99999999999994,"Height":20,"isDefaultProperty":false}],"isDefaultProperty":false},{"PageElementIdentifier":"7430d3ca-e28c-4a25-ba96-f8fe8398f21f","ResourceKey":"Omron.ControlContainers.Group","Name":"Group4","Left":22,"Top":200,"Width":218.00000000000003,"Height":20,"ChildControls":[{"PageElementIdentifier":"15325453-c621-4d67-a24b-669228f408d0","ResourceKey":"Omron.LampControls.BitLamp","Name":"BL_StateBit4","Design":{"v":"Rectangle"},"FontFamily":"abb64941-8677-48f0-80f4-990e6e67b265","FontSize":"e5a8243f-dccc-4c38-9e0e-cecb2fe15b52","FontStyle":"d6142689-6e0f-434d-be90-8b77c008373c","BackgroundColorOn":{"ColorContext":null,"A":255,"R":255,"G":165,"B":0,"ScA":1,"ScR":1,"ScG":0.376262158,"ScB":0},"BorderBrush":{"c":4278190080},"BorderThickness":{"Left":1,"Top":1,"Right":1,"Bottom":1},"Expression":"Value And 16","Top":3,"Width":15,"Height":15,"isDefaultProperty":false},{"PageElementIdentifier":"5a5a6ed3-8612-49e5-a53c-5b0cc34e9375","ResourceKey":"Omron.StandardControls.Label","Name":"L_SafetyBit4","Text":"8d3ba45f-f5b7-406c-82af-2328dba4e30e","FontFamily":"abb64941-8677-48f0-80f4-990e6e67b265","FontSize":"c1cef132-dda3-4ff9-949d-a982fe3fa6a2","FontStyle":"d6142689-6e0f-434d-be90-8b77c008373c","VerticalContentAlignment":{"v":"Center"},"NAPadding":{"Left":2,"Top":1,"Right":2,"Bottom":2},"Left":28,"Width":190.00000000000003,"Height":20,"Animations":[{"PageElementIdentifier":"628c2ee3-b3e9-4b19-884d-acc4e2d50c86","ResourceKey":"Omron.StandardAnimations.Visibility","Name":"____Visibility11","Expression":"Safe","isDefaultProperty":false}],"isDefaultProperty":false},{"PageElementIdentifier":"4b652019-83e8-44d6-9d8e-8929c05afb05","ResourceKey":"Omron.StandardControls.DataDisplay","Name":"D_NameBit4","FontFamily":"abb64941-8677-48f0-80f4-990e6e67b265","FontSize":"e5a8243f-dccc-4c38-9e0e-cecb2fe15b52","FontStyle":"d6142689-6e0f-434d-be90-8b77c008373c","HorizontalContentAlignment":{"v":"Left"},"VerticalContentAlignment":{"v":"Center"},"NAPadding":{"Left":2,"Top":1,"Right":2,"Bottom":2},"Expression":"I0_04","Left":28.000000000000014,"Width":174.99999999999994,"Height":20,"Animations":[{"PageElementIdentifier":"8d1a59c8-8020-4987-83f1-138a2c6e99ee","ResourceKey":"Omron.StandardAnimations.Visibility","Name":"____Visibility0","Expression":"Not Safe","isDefaultProperty":false}],"isDefaultProperty":false}],"isDefaultProperty":false},{"PageElementIdentifier":"1acf1653-dffc-4780-af99-8575b3b81fdc","ResourceKey":"Omron.ControlContainers.Group","Name":"Group5","Left":22,"Top":230,"Width":218.00000000000003,"Height":20,"ChildControls":[{"PageElementIdentifier":"a6a66785-8d19-4c26-83d9-2fcb26866159","ResourceKey":"Omron.LampControls.BitLamp","Name":"BL_StateBit5","Design":{"v":"Rectangle"},"FontFamily":"abb64941-8677-48f0-80f4-990e6e67b265","FontSize":"e5a8243f-dccc-4c38-9e0e-cecb2fe15b52","FontStyle":"d6142689-6e0f-434d-be90-8b77c008373c","BackgroundColorOn":{"ColorContext":null,"A":255,"R":255,"G":165,"B":0,"ScA":1,"ScR":1,"ScG":0.376262158,"ScB":0},"BorderBrush":{"c":4278190080},"BorderThickness":{"Left":1,"Top":1,"Right":1,"Bottom":1},"Expression":"Value And 32","Top":3,"Width":15,"Height":15,"isDefaultProperty":false},{"PageElementIdentifier":"611b21ef-c807-44f2-90b6-5341e551821e","ResourceKey":"Omron.StandardControls.Label","Name":"L_SafetyBit5","Text":"3c9df3ad-db18-4252-af4e-9ecfbb7e9eb7","FontFamily":"abb64941-8677-48f0-80f4-990e6e67b265","FontSize":"c1cef132-dda3-4ff9-949d-a982fe3fa6a2","FontStyle":"d6142689-6e0f-434d-be90-8b77c008373c","VerticalContentAlignment":{"v":"Center"},"NAPadding":{"Left":2,"Top":1,"Right":2,"Bottom":2},"Left":28,"Width":190.00000000000003,"Height":20,"Animations":[{"PageElementIdentifier":"a3fd5856-15de-4554-bd92-92350089d6fd","ResourceKey":"Omron.StandardAnimations.Visibility","Name":"____Visibility10","Expression":"Safe","isDefaultProperty":false}],"isDefaultProperty":false},{"PageElementIdentifier":"c8e3c0e7-801a-4845-b422-188dd1ffa221","ResourceKey":"Omron.StandardControls.DataDisplay","Name":"D_NameBit5","FontFamily":"abb64941-8677-48f0-80f4-990e6e67b265","FontSize":"e5a8243f-dccc-4c38-9e0e-cecb2fe15b52","FontStyle":"d6142689-6e0f-434d-be90-8b77c008373c","HorizontalContentAlignment":{"v":"Left"},"VerticalContentAlignment":{"v":"Center"},"NAPadding":{"Left":2,"Top":1,"Right":2,"Bottom":2},"Expression":"I0_05","Left":28.000000000000014,"Width":174.99999999999994,"Height":20,"Animations":[{"PageElementIdentifier":"027273ea-2cca-47a5-8e17-0d6a6dd61eaf","ResourceKey":"Omron.StandardAnimations.Visibility","Name":"____Visibility1","Expression":"Not Safe","isDefaultProperty":false}],"isDefaultProperty":false}],"isDefaultProperty":false},{"PageElementIdentifier":"af861c60-0958-43f4-a320-cc22123c7ce7","ResourceKey":"Omron.ControlContainers.Group","Name":"Group6","Left":22,"Top":260,"Width":218,"Height":20,"ChildControls":[{"PageElementIdentifier":"f73fad3e-6616-43ef-a0ed-de2812de740c","ResourceKey":"Omron.LampControls.BitLamp","Name":"BL_StateBit6","Design":{"v":"Rectangle"},"FontFamily":"abb64941-8677-48f0-80f4-990e6e67b265","FontSize":"e5a8243f-dccc-4c38-9e0e-cecb2fe15b52","FontStyle":"d6142689-6e0f-434d-be90-8b77c008373c","BackgroundColorOn":{"ColorContext":null,"A":255,"R":255,"G":165,"B":0,"ScA":1,"ScR":1,"ScG":0.376262158,"ScB":0},"BorderBrush":{"c":4278190080},"BorderThickness":{"Left":1,"Top":1,"Right":1,"Bottom":1},"Expression":"Value And 64","Top":3,"Width":15,"Height":15,"isDefaultProperty":false},{"PageElementIdentifier":"c533a880-336b-47fe-944c-f029a8d03ff9","ResourceKey":"Omron.StandardControls.Label","Name":"L_SafetyBit6","Text":"24f749cb-f16c-4a57-82e9-ec7491a6234f","FontFamily":"abb64941-8677-48f0-80f4-990e6e67b265","FontSize":"c1cef132-dda3-4ff9-949d-a982fe3fa6a2","FontStyle":"d6142689-6e0f-434d-be90-8b77c008373c","VerticalContentAlignment":{"v":"Center"},"NAPadding":{"Left":2,"Top":1,"Right":2,"Bottom":2},"Left":28,"Width":190,"Height":20,"Animations":[{"PageElementIdentifier":"03e85f97-4152-4254-a547-3a9188e2639a","ResourceKey":"Omron.StandardAnimations.Visibility","Name":"____Visibility9","Expression":"Safe","isDefaultProperty":false}],"isDefaultProperty":false},{"PageElementIdentifier":"6a73b505-fc56-44f3-b4ec-e42975caae9f","ResourceKey":"Omron.StandardControls.DataDisplay","Name":"D_NameBit6","FontFamily":"abb64941-8677-48f0-80f4-990e6e67b265","FontSize":"e5a8243f-dccc-4c38-9e0e-cecb2fe15b52","FontStyle":"d6142689-6e0f-434d-be90-8b77c008373c","HorizontalContentAlignment":{"v":"Left"},"VerticalContentAlignment":{"v":"Center"},"NAPadding":{"Left":2,"Top":1,"Right":2,"Bottom":2},"Expression":"I0_06","Left":28.000000000000007,"Width":175,"Height":20,"Animations":[{"PageElementIdentifier":"9f29c665-8f78-4fc1-a3a9-683031b37fa3","ResourceKey":"Omron.StandardAnimations.Visibility","Name":"____Visibility2","Expression":"Not Safe","isDefaultProperty":false}],"isDefaultProperty":false}],"isDefaultProperty":false},{"PageElementIdentifier":"6776e5f4-97e0-4ac5-b0a1-555b9c1e5970","ResourceKey":"Omron.ControlContainers.Group","Name":"Group7","Left":22,"Top":290,"Width":218,"Height":20,"ChildControls":[{"PageElementIdentifier":"e25a8652-2bed-436f-aa47-51c7c872bbec","ResourceKey":"Omron.LampControls.BitLamp","Name":"BL_StateBit7","Design":{"v":"Rectangle"},"FontFamily":"abb64941-8677-48f0-80f4-990e6e67b265","FontSize":"e5a8243f-dccc-4c38-9e0e-cecb2fe15b52","FontStyle":"d6142689-6e0f-434d-be90-8b77c008373c","BackgroundColorOn":{"ColorContext":null,"A":255,"R":255,"G":165,"B":0,"ScA":1,"ScR":1,"ScG":0.376262158,"ScB":0},"BorderBrush":{"c":4278190080},"BorderThickness":{"Left":1,"Top":1,"Right":1,"Bottom":1},"Expression":"Value And 128","Top":3,"Width":15,"Height":15,"isDefaultProperty":false},{"PageElementIdentifier":"2a820c47-12ef-4ffb-9316-d9b020022353","ResourceKey":"Omron.StandardControls.Label","Name":"L_SafetyBit7","Text":"a2dac333-8ec2-41d4-8a12-77d93e69098c","FontFamily":"abb64941-8677-48f0-80f4-990e6e67b265","FontSize":"c1cef132-dda3-4ff9-949d-a982fe3fa6a2","FontStyle":"4d0bdc1e-b08a-4961-ba42-7aeb6c5997ac","VerticalContentAlignment":{"v":"Center"},"NAPadding":{"Left":2,"Top":1,"Right":2,"Bottom":2},"Left":28,"Width":190,"Height":20,"Animations":[{"PageElementIdentifier":"de744c5b-e071-496a-9dca-b390094ef630","ResourceKey":"Omron.StandardAnimations.Visibility","Name":"____Visibility8","Expression":"Safe","isDefaultProperty":false}],"isDefaultProperty":false},{"PageElementIdentifier":"1005417d-b117-454b-9aae-bcc16ea45645","ResourceKey":"Omron.StandardControls.DataDisplay","Name":"D_NameBit7","FontFamily":"abb64941-8677-48f0-80f4-990e6e67b265","FontSize":"e5a8243f-dccc-4c38-9e0e-cecb2fe15b52","FontStyle":"d6142689-6e0f-434d-be90-8b77c008373c","HorizontalContentAlignment":{"v":"Left"},"VerticalContentAlignment":{"v":"Center"},"NAPadding":{"Left":2,"Top":1,"Right":2,"Bottom":2},"Expression":"I0_07","Left":28.000000000000014,"Width":174.99999999999994,"Height":20,"Animations":[{"PageElementIdentifier":"cb7b9620-f8b0-456b-84b3-fa1c7fd4a0ae","ResourceKey":"Omron.StandardAnimations.Visibility","Name":"____Visibility3","Expression":"Not Safe","isDefaultProperty":false}],"isDefaultProperty":false}],"isDefaultProperty":false},{"PageElementIdentifier":"827dea52-0945-45e6-a524-380a9ba10442","ResourceKey":"Omron.ControlContainers.Group","Name":"G_Text0","Top":55,"Width":240,"Height":20,"ChildControls":[{"PageElementIdentifier":"3688eff6-81b3-4279-8ffb-37d4952412bf","ResourceKey":"Omron.StandardControls.Label","Name":"L_VariableName","Text":"33ebc325-a005-45a4-a756-e7d7e4af5d63","FontFamily":"abb64941-8677-48f0-80f4-990e6e67b265","FontSize":"c1cef132-dda3-4ff9-949d-a982fe3fa6a2","FontStyle":"e685da6d-30b0-4c13-8ad4-387acbccd74e","HorizontalContentAlignment":{"v":"Center"},"VerticalContentAlignment":{"v":"Center"},"Left":60,"Width":180,"Height":20,"isDefaultProperty":false},{"PageElementIdentifier":"79047ce4-c890-418a-b3d4-c7e7eb6f5227","ResourceKey":"Omron.StandardControls.Label","Name":"L_VariableState","Text":"84c0273f-efca-4f78-a74c-d25a33315c8f","FontFamily":"abb64941-8677-48f0-80f4-990e6e67b265","FontSize":"c1cef132-dda3-4ff9-949d-a982fe3fa6a2","FontStyle":"e685da6d-30b0-4c13-8ad4-387acbccd74e","HorizontalContentAlignment":{"v":"Center"},"VerticalContentAlignment":{"v":"Center"},"Width":60,"Height":20,"isDefaultProperty":false}],"isDefaultProperty":false},{"PageElementIdentifier":"8f3bdfd2-5650-42a9-b3a4-69f1fe4db84a","ResourceKey":"Omron.ControlContainers.Group","Name":"G_DigitalOutputCard","Top":35,"Width":245,"Height":20,"ChildControls":[{"PageElementIdentifier":"27a09811-50ca-467d-a5ba-2dcc8bc0eef8","ResourceKey":"Omron.StandardShapes.Polygon","Name":"P_DigitalOutputCard","Fill":{"c":4294967040},"Stroke":{"c":16777215},"Data":{"pg":"F0 M 240,0 L 20,0 L 0,20 L 220,20 L 240,0 Z"},"Left":5,"Width":240,"Height":20,"isDefaultProperty":false},{"PageElementIdentifier":"b1496d41-5cfc-41ab-b19c-7e708a8c4857","ResourceKey":"Omron.StandardControls.Label","Name":"L_DigitalOutputCard","Text":"36072b6a-ae9b-4d42-b707-94ddc666a94f","FontFamily":"abb64941-8677-48f0-80f4-990e6e67b265","FontSize":"e5a8243f-dccc-4c38-9e0e-cecb2fe15b52","FontStyle":"fe6ce249-0ac2-4517-90fb-a82bcebf8a46","HorizontalContentAlignment":{"v":"Center"},"VerticalContentAlignment":{"v":"Center"},"Foreground":{"c":4278190080},"Width":239.99999999999997,"Height":20,"isDefaultProperty":false}],"Animations":[{"PageElementIdentifier":"0ea791a5-7f7a-4e2b-9a13-de606cd4bf1c","ResourceKey":"Omron.StandardAnimations.Visibility","Name":"____Visibility5","Expression":"CardType = _eIO_CARD_TYPE.DigitalOutput And Not Safe","isDefaultProperty":false}],"isDefaultProperty":false},{"PageElementIdentifier":"fefea228-4b77-4689-96da-67b9b9280a84","ResourceKey":"Omron.ControlContainers.Group","Name":"G_SafetyOutputCard","Top":35,"Width":245,"Height":20,"ChildControls":[{"PageElementIdentifier":"eee50fd9-6521-4d10-a20b-cf80816e8066","ResourceKey":"Omron.StandardShapes.Polygon","Name":"P_SafetyOutputCard","Fill":{"c":4294901760},"Stroke":{"c":16777215},"Data":{"pg":"F0 M 240,0 L 20,0 L 0,20 L 220,20 L 240,0 Z"},"Left":5,"Width":240,"Height":20,"isDefaultProperty":false},{"PageElementIdentifier":"6e7f7e14-db0a-4ef4-b63c-05a639224feb","ResourceKey":"Omron.StandardControls.Label","Name":"L_SafetyOutputCard","Text":"aced4db2-a566-4880-a2de-a47c498e77fb","FontFamily":"abb64941-8677-48f0-80f4-990e6e67b265","FontSize":"f4eeab15-5593-45fa-88f3-e8a2e2c8afdd","FontStyle":"fe6ce249-0ac2-4517-90fb-a82bcebf8a46","HorizontalContentAlignment":{"v":"Center"},"VerticalContentAlignment":{"v":"Center"},"Foreground":{"c":4278190080},"Width":239.99999999999997,"Height":20,"isDefaultProperty":false}],"Animations":[{"PageElementIdentifier":"638c65e9-c2d2-48a1-bf47-56e84df6051c","ResourceKey":"Omron.StandardAnimations.Visibility","Name":"____Visibility6","Expression":"CardType = _eIO_CARD_TYPE.DigitalOutput And Safe","isDefaultProperty":false}],"isDefaultProperty":false},{"PageElementIdentifier":"72158a84-37ab-479a-9523-bea9130cdab1","ResourceKey":"Omron.ControlContainers.Group","Name":"G_SafetyInputCard","Top":35,"Width":245,"Height":20,"ChildControls":[{"PageElementIdentifier":"3cb03183-d2d7-4651-b1d4-9df311e1641a","ResourceKey":"Omron.StandardShapes.Polygon","Name":"P_SafetyInputCard","Fill":{"c":4294901760},"Stroke":{"c":16777215},"Data":{"pg":"F0 M 240,0 L 20,0 L 0,20 L 220,20 L 240,0 Z"},"Left":5,"Width":240,"Height":20,"isDefaultProperty":false},{"PageElementIdentifier":"0b923759-e7b7-4991-8e4a-67c2f8414bbc","ResourceKey":"Omron.StandardControls.Label","Name":"L_SafetyInputCard","Text":"97a422f0-4afa-4c2e-87d9-6730193e812f","FontFamily":"abb64941-8677-48f0-80f4-990e6e67b265","FontSize":"f4f0dfe7-b36f-422f-91a8-44498d5b185d","FontStyle":"fe6ce249-0ac2-4517-90fb-a82bcebf8a46","HorizontalContentAlignment":{"v":"Center"},"VerticalContentAlignment":{"v":"Center"},"Foreground":{"c":4278190080},"Width":240.00000000000003,"Height":20,"isDefaultProperty":false}],"Animations":[{"PageElementIdentifier":"cd94eb77-bde5-40f0-a1c2-6f94396a10ae","ResourceKey":"Omron.StandardAnimations.Visibility","Name":"____Visibility7","Expression":"CardType = _eIO_CARD_TYPE.DigitalInput And Safe","isDefaultProperty":false}],"isDefaultProperty":false},{"PageElementIdentifier":"65065cff-6f3b-4ef7-9dde-cf9f8d489534","ResourceKey":"Omron.ControlContainers.Group","Name":"G_DigitalInputCard","Left":-2.8421709430404007E-14,"Top":35,"Width":245.00000000000003,"Height":20,"ChildControls":[{"PageElementIdentifier":"228f4dd9-54a4-4664-9cf7-f2e846c4a935","ResourceKey":"Omron.StandardShapes.Polygon","Name":"P_DigitalInputCard","Fill":{"c":4294944000},"Stroke":{"c":16777215},"Data":{"pg":"F0 M 240,0 L 20,0 L 0,20 L 220,20 L 240,0 Z"},"Left":5.0000000000000284,"Width":240,"Height":20,"isDefaultProperty":false},{"PageElementIdentifier":"8cf0f9d3-1510-4cb0-85c7-0806a255af64","ResourceKey":"Omron.StandardControls.Label","Name":"L_DigitalInputCard","Text":"a0ce662c-673b-48fb-b821-b0610a45a2a7","FontFamily":"abb64941-8677-48f0-80f4-990e6e67b265","FontSize":"e5a8243f-dccc-4c38-9e0e-cecb2fe15b52","FontStyle":"fe6ce249-0ac2-4517-90fb-a82bcebf8a46","HorizontalContentAlignment":{"v":"Center"},"VerticalContentAlignment":{"v":"Center"},"Foreground":{"c":4278190080},"Width":240.00000000000006,"Height":20,"isDefaultProperty":false}],"Animations":[{"PageElementIdentifier":"767bb2aa-0308-442e-a498-216013440a42","ResourceKey":"Omron.StandardAnimations.Visibility","Name":"____Visibility4","Expression":"CardType = _eIO_CARD_TYPE.DigitalInput And Not Safe","isDefaultProperty":false}],"isDefaultProperty":false},{"PageElementIdentifier":"88b4c72f-b4c2-4f78-9835-64e84eb43663","ResourceKey":"Omron.StandardShapes.Line","Name":"S_Line1","Stroke":{"c":4278190080},"Data":{"pg":"F0 M 230,0 L 0,0 "},"Left":10,"Top":75,"Width":230,"Height":1,"isDefaultProperty":false}],"serialData":{},"serialCodeData":{},"serialScalingData":{},"isDefaultProperty":false}