<?xml version="1.0" encoding="utf-8"?>
<IagResources>
  <Resources Type="Strings">
    <Resource Name="State_Execute" ID="725e6601-de65-43b6-a31b-8225310e7873">
      <Localisation Language="en-GB" Translation="Execute" Default="True" />
      <Localisation Language="tr-TR" Translation="" />
      <Localisation Language="it-IT" Translation="" />
      <Localisation Language="es-ES" Translation="" />
      <Localisation Language="pt-PT" Translation="" />
      <Localisation Language="fr-CH" Translation="" />
      <Localisation Language="de-DE" Translation="" />
      <Localisation Language="ru-RU" Translation="" />
      <Localisation Language="bg-BG" Translation="" />
      <Localisation Language="sv-SE" Translation="" />
    </Resource>
    <Resource Name="State_Starting" ID="b6f2e1b1-e948-462b-b6de-f3b1a67632ea">
      <Localisation Language="en-GB" Translation="Starting" Default="True" />
      <Localisation Language="tr-TR" Translation="" />
      <Localisation Language="it-IT" Translation="" />
      <Localisation Language="es-ES" Translation="" />
      <Localisation Language="pt-PT" Translation="" />
      <Localisation Language="fr-CH" Translation="" />
      <Localisation Language="de-DE" Translation="" />
      <Localisation Language="ru-RU" Translation="" />
      <Localisation Language="bg-BG" Translation="" />
      <Localisation Language="sv-SE" Translation="" />
    </Resource>
    <Resource Name="String120" ID="b14d4463-38a4-48bc-bf1f-8241d6709057">
      <Localisation Language="en-GB" Translation="Held" Default="True" />
      <Localisation Language="tr-TR" Translation="" />
      <Localisation Language="it-IT" Translation="" />
      <Localisation Language="es-ES" Translation="" />
      <Localisation Language="pt-PT" Translation="" />
      <Localisation Language="fr-CH" Translation="" />
      <Localisation Language="de-DE" Translation="" />
      <Localisation Language="ru-RU" Translation="" />
      <Localisation Language="bg-BG" Translation="" />
      <Localisation Language="sv-SE" Translation="" />
    </Resource>
    <Resource Name="String121" ID="1d262015-dc05-4855-9f6b-70e0720a1e4d">
      <Localisation Language="en-GB" Translation="Holding" Default="True" />
      <Localisation Language="tr-TR" Translation="" />
      <Localisation Language="it-IT" Translation="" />
      <Localisation Language="es-ES" Translation="" />
      <Localisation Language="pt-PT" Translation="" />
      <Localisation Language="fr-CH" Translation="" />
      <Localisation Language="de-DE" Translation="" />
      <Localisation Language="ru-RU" Translation="" />
      <Localisation Language="bg-BG" Translation="" />
      <Localisation Language="sv-SE" Translation="" />
    </Resource>
    <Resource Name="String122" ID="427a8efe-e2fc-4715-8fd5-6e4e296f51f5">
      <Localisation Language="en-GB" Translation="Hold" Default="True" />
      <Localisation Language="tr-TR" Translation="" />
      <Localisation Language="it-IT" Translation="" />
      <Localisation Language="es-ES" Translation="" />
      <Localisation Language="pt-PT" Translation="" />
      <Localisation Language="fr-CH" Translation="" />
      <Localisation Language="de-DE" Translation="" />
      <Localisation Language="ru-RU" Translation="" />
      <Localisation Language="bg-BG" Translation="" />
      <Localisation Language="sv-SE" Translation="" />
    </Resource>
    <Resource Name="String124" ID="0147e8bc-246f-424f-ba72-fc0a2b72c2dd">
      <Localisation Language="en-GB" Translation="Un-holding" Default="True" />
      <Localisation Language="tr-TR" Translation="" />
      <Localisation Language="it-IT" Translation="" />
      <Localisation Language="es-ES" Translation="" />
      <Localisation Language="pt-PT" Translation="" />
      <Localisation Language="fr-CH" Translation="" />
      <Localisation Language="de-DE" Translation="" />
      <Localisation Language="ru-RU" Translation="" />
      <Localisation Language="bg-BG" Translation="" />
      <Localisation Language="sv-SE" Translation="" />
    </Resource>
    <Resource Name="String16" ID="ee0b8986-d04f-4f85-8d68-1a067db11388">
      <Localisation Language="en-GB" Translation="Run" Default="True" />
      <Localisation Language="tr-TR" Translation="" />
      <Localisation Language="it-IT" Translation="" />
      <Localisation Language="es-ES" Translation="" />
      <Localisation Language="pt-PT" Translation="" />
      <Localisation Language="fr-CH" Translation="" />
      <Localisation Language="de-DE" Translation="" />
      <Localisation Language="ru-RU" Translation="" />
      <Localisation Language="bg-BG" Translation="" />
      <Localisation Language="sv-SE" Translation="" />
    </Resource>
    <Resource Name="String25" ID="d6bdf0a8-120f-49f6-946d-335abb5e35dc">
      <Localisation Language="en-GB" Translation="Un-Suspending" Default="True" />
      <Localisation Language="tr-TR" Translation="" />
      <Localisation Language="it-IT" Translation="" />
      <Localisation Language="es-ES" Translation="" />
      <Localisation Language="pt-PT" Translation="" />
      <Localisation Language="fr-CH" Translation="" />
      <Localisation Language="de-DE" Translation="" />
      <Localisation Language="ru-RU" Translation="" />
      <Localisation Language="bg-BG" Translation="" />
      <Localisation Language="sv-SE" Translation="" />
    </Resource>
    <Resource Name="String26" ID="059d900d-de36-45b3-a6d0-8eb4c584eb87">
      <Localisation Language="en-GB" Translation="Aborted" Default="True" />
      <Localisation Language="tr-TR" Translation="" />
      <Localisation Language="it-IT" Translation="" />
      <Localisation Language="es-ES" Translation="" />
      <Localisation Language="pt-PT" Translation="" />
      <Localisation Language="fr-CH" Translation="" />
      <Localisation Language="de-DE" Translation="" />
      <Localisation Language="ru-RU" Translation="" />
      <Localisation Language="bg-BG" Translation="" />
      <Localisation Language="sv-SE" Translation="" />
    </Resource>
    <Resource Name="String27" ID="b8067898-d555-43f9-84d7-c30b06fccbeb">
      <Localisation Language="en-GB" Translation="Aborting" Default="True" />
      <Localisation Language="tr-TR" Translation="" />
      <Localisation Language="it-IT" Translation="" />
      <Localisation Language="es-ES" Translation="" />
      <Localisation Language="pt-PT" Translation="" />
      <Localisation Language="fr-CH" Translation="" />
      <Localisation Language="de-DE" Translation="" />
      <Localisation Language="ru-RU" Translation="" />
      <Localisation Language="bg-BG" Translation="" />
      <Localisation Language="sv-SE" Translation="" />
    </Resource>
    <Resource Name="String28" ID="7d7ebb41-d103-41b0-a9e3-526b4e3802d2">
      <Localisation Language="en-GB" Translation="Clearing" Default="True" />
      <Localisation Language="tr-TR" Translation="" />
      <Localisation Language="it-IT" Translation="" />
      <Localisation Language="es-ES" Translation="" />
      <Localisation Language="pt-PT" Translation="" />
      <Localisation Language="fr-CH" Translation="" />
      <Localisation Language="de-DE" Translation="" />
      <Localisation Language="ru-RU" Translation="" />
      <Localisation Language="bg-BG" Translation="" />
      <Localisation Language="sv-SE" Translation="" />
    </Resource>
    <Resource Name="String29" ID="91d271da-8032-4cea-9cac-6c82b13e8673">
      <Localisation Language="en-GB" Translation="Stopping" Default="True" />
      <Localisation Language="tr-TR" Translation="" />
      <Localisation Language="it-IT" Translation="" />
      <Localisation Language="es-ES" Translation="" />
      <Localisation Language="pt-PT" Translation="" />
      <Localisation Language="fr-CH" Translation="" />
      <Localisation Language="de-DE" Translation="" />
      <Localisation Language="ru-RU" Translation="" />
      <Localisation Language="bg-BG" Translation="" />
      <Localisation Language="sv-SE" Translation="" />
    </Resource>
    <Resource Name="String30" ID="9741e4ed-8fc5-42cc-9031-16771737c65d">
      <Localisation Language="en-GB" Translation="Stopped" Default="True" />
      <Localisation Language="tr-TR" Translation="" />
      <Localisation Language="it-IT" Translation="" />
      <Localisation Language="es-ES" Translation="" />
      <Localisation Language="pt-PT" Translation="" />
      <Localisation Language="fr-CH" Translation="" />
      <Localisation Language="de-DE" Translation="" />
      <Localisation Language="ru-RU" Translation="" />
      <Localisation Language="bg-BG" Translation="" />
      <Localisation Language="sv-SE" Translation="" />
    </Resource>
    <Resource Name="String31" ID="202b9b10-a10d-4b5e-9445-19982fea8457">
      <Localisation Language="en-GB" Translation="Resetting" Default="True" />
      <Localisation Language="tr-TR" Translation="" />
      <Localisation Language="it-IT" Translation="" />
      <Localisation Language="es-ES" Translation="" />
      <Localisation Language="pt-PT" Translation="" />
      <Localisation Language="fr-CH" Translation="" />
      <Localisation Language="de-DE" Translation="" />
      <Localisation Language="ru-RU" Translation="" />
      <Localisation Language="bg-BG" Translation="" />
      <Localisation Language="sv-SE" Translation="" />
    </Resource>
    <Resource Name="String32" ID="c3f57d27-8f2d-4a1f-b1b8-42a0d2e72c31">
      <Localisation Language="en-GB" Translation="Idle" Default="True" />
      <Localisation Language="tr-TR" Translation="" />
      <Localisation Language="it-IT" Translation="" />
      <Localisation Language="es-ES" Translation="" />
      <Localisation Language="pt-PT" Translation="" />
      <Localisation Language="fr-CH" Translation="" />
      <Localisation Language="de-DE" Translation="" />
      <Localisation Language="ru-RU" Translation="" />
      <Localisation Language="bg-BG" Translation="" />
      <Localisation Language="sv-SE" Translation="" />
    </Resource>
    <Resource Name="String33" ID="aa0f1847-a3be-4300-8b94-5b424287403c">
      <Localisation Language="en-GB" Translation="Complete" Default="True" />
      <Localisation Language="tr-TR" Translation="" />
      <Localisation Language="it-IT" Translation="" />
      <Localisation Language="es-ES" Translation="" />
      <Localisation Language="pt-PT" Translation="" />
      <Localisation Language="fr-CH" Translation="" />
      <Localisation Language="de-DE" Translation="" />
      <Localisation Language="ru-RU" Translation="" />
      <Localisation Language="bg-BG" Translation="" />
      <Localisation Language="sv-SE" Translation="" />
    </Resource>
    <Resource Name="String34" ID="8740942c-218e-446a-8a93-a88a915e6c43">
      <Localisation Language="en-GB" Translation="Suspending" Default="True" />
      <Localisation Language="tr-TR" Translation="" />
      <Localisation Language="it-IT" Translation="" />
      <Localisation Language="es-ES" Translation="" />
      <Localisation Language="pt-PT" Translation="" />
      <Localisation Language="fr-CH" Translation="" />
      <Localisation Language="de-DE" Translation="" />
      <Localisation Language="ru-RU" Translation="" />
      <Localisation Language="bg-BG" Translation="" />
      <Localisation Language="sv-SE" Translation="" />
    </Resource>
    <Resource Name="String35" ID="b6d0b0d2-ffbe-4a51-af25-015de416a4a8">
      <Localisation Language="en-GB" Translation="Suspended" Default="True" />
      <Localisation Language="tr-TR" Translation="" />
      <Localisation Language="it-IT" Translation="" />
      <Localisation Language="es-ES" Translation="" />
      <Localisation Language="pt-PT" Translation="" />
      <Localisation Language="fr-CH" Translation="" />
      <Localisation Language="de-DE" Translation="" />
      <Localisation Language="ru-RU" Translation="" />
      <Localisation Language="bg-BG" Translation="" />
      <Localisation Language="sv-SE" Translation="" />
    </Resource>
    <Resource Name="String38" ID="64f17500-4481-42b5-85b3-564496b56744">
      <Localisation Language="en-GB" Translation="Start" Default="True" />
      <Localisation Language="tr-TR" Translation="" />
      <Localisation Language="it-IT" Translation="" />
      <Localisation Language="es-ES" Translation="" />
      <Localisation Language="pt-PT" Translation="" />
      <Localisation Language="fr-CH" Translation="" />
      <Localisation Language="de-DE" Translation="" />
      <Localisation Language="ru-RU" Translation="" />
      <Localisation Language="bg-BG" Translation="" />
      <Localisation Language="sv-SE" Translation="" />
    </Resource>
    <Resource Name="String39" ID="01b5008f-36a2-4364-bc50-d3c308cbe848">
      <Localisation Language="en-GB" Translation="Reset" Default="True" />
      <Localisation Language="tr-TR" Translation="" />
      <Localisation Language="it-IT" Translation="" />
      <Localisation Language="es-ES" Translation="" />
      <Localisation Language="pt-PT" Translation="" />
      <Localisation Language="fr-CH" Translation="" />
      <Localisation Language="de-DE" Translation="" />
      <Localisation Language="ru-RU" Translation="" />
      <Localisation Language="bg-BG" Translation="" />
      <Localisation Language="sv-SE" Translation="" />
    </Resource>
    <Resource Name="String40" ID="6d455d03-043f-4611-ab00-ae5fc4f42f46">
      <Localisation Language="en-GB" Translation="Stop" Default="True" />
      <Localisation Language="tr-TR" Translation="" />
      <Localisation Language="it-IT" Translation="" />
      <Localisation Language="es-ES" Translation="" />
      <Localisation Language="pt-PT" Translation="" />
      <Localisation Language="fr-CH" Translation="" />
      <Localisation Language="de-DE" Translation="" />
      <Localisation Language="ru-RU" Translation="" />
      <Localisation Language="bg-BG" Translation="" />
      <Localisation Language="sv-SE" Translation="" />
    </Resource>
    <Resource Name="String41" ID="0cc4053f-06cb-49a8-8b1e-29652c811d17">
      <Localisation Language="en-GB" Translation="Clear" Default="True" />
      <Localisation Language="tr-TR" Translation="" />
      <Localisation Language="it-IT" Translation="" />
      <Localisation Language="es-ES" Translation="" />
      <Localisation Language="pt-PT" Translation="" />
      <Localisation Language="fr-CH" Translation="" />
      <Localisation Language="de-DE" Translation="" />
      <Localisation Language="ru-RU" Translation="" />
      <Localisation Language="bg-BG" Translation="" />
      <Localisation Language="sv-SE" Translation="" />
    </Resource>
    <Resource Name="String42" ID="c958c924-32f9-4335-bd59-f2960238e975">
      <Localisation Language="en-GB" Translation="Abort" Default="True" />
      <Localisation Language="tr-TR" Translation="" />
      <Localisation Language="it-IT" Translation="" />
      <Localisation Language="es-ES" Translation="" />
      <Localisation Language="pt-PT" Translation="" />
      <Localisation Language="fr-CH" Translation="" />
      <Localisation Language="de-DE" Translation="" />
      <Localisation Language="ru-RU" Translation="" />
      <Localisation Language="bg-BG" Translation="" />
      <Localisation Language="sv-SE" Translation="" />
    </Resource>
    <Resource Name="String43" ID="805fb462-be37-43eb-ba6f-6ff2e9afd98a">
      <Localisation Language="en-GB" Translation="Suspend" Default="True" />
      <Localisation Language="tr-TR" Translation="" />
      <Localisation Language="it-IT" Translation="" />
      <Localisation Language="es-ES" Translation="" />
      <Localisation Language="pt-PT" Translation="" />
      <Localisation Language="fr-CH" Translation="" />
      <Localisation Language="de-DE" Translation="" />
      <Localisation Language="ru-RU" Translation="" />
      <Localisation Language="bg-BG" Translation="" />
      <Localisation Language="sv-SE" Translation="" />
    </Resource>
    <Resource Name="String46" ID="483ed46e-3357-4b22-8114-eadeb59098d5">
      <Localisation Language="en-GB" Translation="Keys" Default="True" />
      <Localisation Language="tr-TR" Translation="" />
      <Localisation Language="it-IT" Translation="" />
      <Localisation Language="es-ES" Translation="" />
      <Localisation Language="pt-PT" Translation="" />
      <Localisation Language="fr-CH" Translation="" />
      <Localisation Language="de-DE" Translation="" />
      <Localisation Language="ru-RU" Translation="" />
      <Localisation Language="bg-BG" Translation="" />
      <Localisation Language="sv-SE" Translation="" />
    </Resource>
    <Resource Name="String47" ID="44bc8932-4cbd-4eae-a87a-bfd6c6510fac">
      <Localisation Language="en-GB" Translation="Abort = Command" Default="True" />
      <Localisation Language="tr-TR" Translation="" />
      <Localisation Language="it-IT" Translation="" />
      <Localisation Language="es-ES" Translation="" />
      <Localisation Language="pt-PT" Translation="" />
      <Localisation Language="fr-CH" Translation="" />
      <Localisation Language="de-DE" Translation="" />
      <Localisation Language="ru-RU" Translation="" />
      <Localisation Language="bg-BG" Translation="" />
      <Localisation Language="sv-SE" Translation="" />
    </Resource>
    <Resource Name="String48" ID="e2381a0b-fca7-4a36-acc8-cc2643db9fcf">
      <Localisation Language="en-GB" Translation="SC = State complete" Default="True" />
      <Localisation Language="tr-TR" Translation="" />
      <Localisation Language="it-IT" Translation="" />
      <Localisation Language="es-ES" Translation="" />
      <Localisation Language="pt-PT" Translation="" />
      <Localisation Language="fr-CH" Translation="" />
      <Localisation Language="de-DE" Translation="" />
      <Localisation Language="ru-RU" Translation="" />
      <Localisation Language="bg-BG" Translation="" />
      <Localisation Language="sv-SE" Translation="" />
    </Resource>
    <Resource Name="String49" ID="b910d9fc-58cf-4581-81fa-865c53090fcf">
      <Localisation Language="en-GB" Translation="Wait State" Default="True" />
      <Localisation Language="tr-TR" Translation="" />
      <Localisation Language="it-IT" Translation="" />
      <Localisation Language="es-ES" Translation="" />
      <Localisation Language="pt-PT" Translation="" />
      <Localisation Language="fr-CH" Translation="" />
      <Localisation Language="de-DE" Translation="" />
      <Localisation Language="ru-RU" Translation="" />
      <Localisation Language="bg-BG" Translation="" />
      <Localisation Language="sv-SE" Translation="" />
    </Resource>
    <Resource Name="String5" ID="ba3e5509-38b2-413b-8ce5-7901bcc2645b">
      <Localisation Language="en-GB" Translation="Work" Default="True" />
      <Localisation Language="tr-TR" Translation="" />
      <Localisation Language="it-IT" Translation="" />
      <Localisation Language="es-ES" Translation="" />
      <Localisation Language="pt-PT" Translation="" />
      <Localisation Language="fr-CH" Translation="" />
      <Localisation Language="de-DE" Translation="" />
      <Localisation Language="ru-RU" Translation="" />
      <Localisation Language="bg-BG" Translation="" />
      <Localisation Language="sv-SE" Translation="" />
    </Resource>
    <Resource Name="String50" ID="20c70373-9393-40f8-be72-2951b943930b">
      <Localisation Language="en-GB" Translation="Acting State" Default="True" />
      <Localisation Language="tr-TR" Translation="" />
      <Localisation Language="it-IT" Translation="" />
      <Localisation Language="es-ES" Translation="" />
      <Localisation Language="pt-PT" Translation="" />
      <Localisation Language="fr-CH" Translation="" />
      <Localisation Language="de-DE" Translation="" />
      <Localisation Language="ru-RU" Translation="" />
      <Localisation Language="bg-BG" Translation="" />
      <Localisation Language="sv-SE" Translation="" />
    </Resource>
    <Resource Name="String51" ID="f341d6cb-531e-433d-9023-e43f4ca8b445">
      <Localisation Language="en-GB" Translation="Actual State" Default="True" />
      <Localisation Language="tr-TR" Translation="" />
      <Localisation Language="it-IT" Translation="" />
      <Localisation Language="es-ES" Translation="" />
      <Localisation Language="pt-PT" Translation="" />
      <Localisation Language="fr-CH" Translation="" />
      <Localisation Language="de-DE" Translation="" />
      <Localisation Language="ru-RU" Translation="" />
      <Localisation Language="bg-BG" Translation="" />
      <Localisation Language="sv-SE" Translation="" />
    </Resource>
    <Resource Name="String6" ID="bf036d2f-8d2f-482f-ae7d-ff138a2fde84">
      <Localisation Language="en-GB" Translation="Ready" Default="True" />
      <Localisation Language="tr-TR" Translation="" />
      <Localisation Language="it-IT" Translation="" />
      <Localisation Language="es-ES" Translation="" />
      <Localisation Language="pt-PT" Translation="" />
      <Localisation Language="fr-CH" Translation="" />
      <Localisation Language="de-DE" Translation="" />
      <Localisation Language="ru-RU" Translation="" />
      <Localisation Language="bg-BG" Translation="" />
      <Localisation Language="sv-SE" Translation="" />
    </Resource>
  </Resources>
  <Resources Type="FontSizes">
    <Resource Name="FontSize" ID="29107d8d-9e28-47b2-a776-feabc79c3e93">
      <Localisation Language="en-GB" Translation="14" Default="True" />
      <Localisation Language="tr-TR" Translation="14" />
      <Localisation Language="it-IT" Translation="14" />
      <Localisation Language="es-ES" Translation="14" />
      <Localisation Language="pt-PT" Translation="14" />
      <Localisation Language="fr-CH" Translation="14" />
      <Localisation Language="de-DE" Translation="14" />
      <Localisation Language="ru-RU" Translation="14" />
      <Localisation Language="bg-BG" Translation="14" />
      <Localisation Language="sv-SE" Translation="14" />
    </Resource>
    <Resource Name="FontSize133" ID="7504e500-d6a0-4977-a972-cc9a46dab5d1">
      <Localisation Language="en-GB" Translation="14" Default="True" />
      <Localisation Language="tr-TR" Translation="14" />
      <Localisation Language="it-IT" Translation="14" />
      <Localisation Language="es-ES" Translation="14" />
      <Localisation Language="pt-PT" Translation="14" />
      <Localisation Language="fr-CH" Translation="14" />
      <Localisation Language="de-DE" Translation="14" />
      <Localisation Language="ru-RU" Translation="14" />
      <Localisation Language="bg-BG" Translation="14" />
      <Localisation Language="sv-SE" Translation="14" />
    </Resource>
    <Resource Name="FontSize134" ID="f44bc09d-e95c-4b72-bee2-255d44f35803">
      <Localisation Language="en-GB" Translation="14" Default="True" />
      <Localisation Language="tr-TR" Translation="14" />
      <Localisation Language="it-IT" Translation="14" />
      <Localisation Language="es-ES" Translation="14" />
      <Localisation Language="pt-PT" Translation="14" />
      <Localisation Language="fr-CH" Translation="14" />
      <Localisation Language="de-DE" Translation="14" />
      <Localisation Language="ru-RU" Translation="14" />
      <Localisation Language="bg-BG" Translation="14" />
      <Localisation Language="sv-SE" Translation="14" />
    </Resource>
    <Resource Name="FontSize135" ID="586d5014-a0ec-4d98-9086-73cd82bb09a1">
      <Localisation Language="en-GB" Translation="14" Default="True" />
      <Localisation Language="tr-TR" Translation="14" />
      <Localisation Language="it-IT" Translation="14" />
      <Localisation Language="es-ES" Translation="14" />
      <Localisation Language="pt-PT" Translation="14" />
      <Localisation Language="fr-CH" Translation="14" />
      <Localisation Language="de-DE" Translation="14" />
      <Localisation Language="ru-RU" Translation="14" />
      <Localisation Language="bg-BG" Translation="14" />
      <Localisation Language="sv-SE" Translation="14" />
    </Resource>
    <Resource Name="FontSize136" ID="8eff9c9e-37fb-4480-af85-552a0a47c109">
      <Localisation Language="en-GB" Translation="10" Default="True" />
      <Localisation Language="tr-TR" Translation="10" />
      <Localisation Language="it-IT" Translation="10" />
      <Localisation Language="es-ES" Translation="10" />
      <Localisation Language="pt-PT" Translation="10" />
      <Localisation Language="fr-CH" Translation="10" />
      <Localisation Language="de-DE" Translation="10" />
      <Localisation Language="ru-RU" Translation="10" />
      <Localisation Language="bg-BG" Translation="10" />
      <Localisation Language="sv-SE" Translation="10" />
    </Resource>
    <Resource Name="FontSize137" ID="9fd56b31-f9c2-4f7e-8cdd-1b5d4b0b6805">
      <Localisation Language="en-GB" Translation="10" Default="True" />
      <Localisation Language="tr-TR" Translation="10" />
      <Localisation Language="it-IT" Translation="10" />
      <Localisation Language="es-ES" Translation="10" />
      <Localisation Language="pt-PT" Translation="10" />
      <Localisation Language="fr-CH" Translation="10" />
      <Localisation Language="de-DE" Translation="10" />
      <Localisation Language="ru-RU" Translation="10" />
      <Localisation Language="bg-BG" Translation="10" />
      <Localisation Language="sv-SE" Translation="10" />
    </Resource>
    <Resource Name="FontSize138" ID="3cb1e9b7-8e4a-4f98-a9e0-38a46e3fc426">
      <Localisation Language="en-GB" Translation="10" Default="True" />
      <Localisation Language="tr-TR" Translation="10" />
      <Localisation Language="it-IT" Translation="10" />
      <Localisation Language="es-ES" Translation="10" />
      <Localisation Language="pt-PT" Translation="10" />
      <Localisation Language="fr-CH" Translation="10" />
      <Localisation Language="de-DE" Translation="10" />
      <Localisation Language="ru-RU" Translation="10" />
      <Localisation Language="bg-BG" Translation="10" />
      <Localisation Language="sv-SE" Translation="10" />
    </Resource>
    <Resource Name="FontSize139" ID="7e2cd075-58d5-4815-8e47-6c1903ecb974">
      <Localisation Language="en-GB" Translation="10" Default="True" />
      <Localisation Language="tr-TR" Translation="10" />
      <Localisation Language="it-IT" Translation="10" />
      <Localisation Language="es-ES" Translation="10" />
      <Localisation Language="pt-PT" Translation="10" />
      <Localisation Language="fr-CH" Translation="10" />
      <Localisation Language="de-DE" Translation="10" />
      <Localisation Language="ru-RU" Translation="10" />
      <Localisation Language="bg-BG" Translation="10" />
      <Localisation Language="sv-SE" Translation="10" />
    </Resource>
    <Resource Name="FontSize140" ID="d6a7b433-6453-475f-ac82-528fb06b77b1">
      <Localisation Language="en-GB" Translation="10" Default="True" />
      <Localisation Language="tr-TR" Translation="10" />
      <Localisation Language="it-IT" Translation="10" />
      <Localisation Language="es-ES" Translation="10" />
      <Localisation Language="pt-PT" Translation="10" />
      <Localisation Language="fr-CH" Translation="10" />
      <Localisation Language="de-DE" Translation="10" />
      <Localisation Language="ru-RU" Translation="10" />
      <Localisation Language="bg-BG" Translation="10" />
      <Localisation Language="sv-SE" Translation="12" />
    </Resource>
    <Resource Name="FontSize141" ID="eab935ad-4f42-4425-a1a3-065cf213254b">
      <Localisation Language="en-GB" Translation="10" Default="True" />
      <Localisation Language="tr-TR" Translation="10" />
      <Localisation Language="it-IT" Translation="10" />
      <Localisation Language="es-ES" Translation="10" />
      <Localisation Language="pt-PT" Translation="10" />
      <Localisation Language="fr-CH" Translation="10" />
      <Localisation Language="de-DE" Translation="10" />
      <Localisation Language="ru-RU" Translation="10" />
      <Localisation Language="bg-BG" Translation="10" />
      <Localisation Language="sv-SE" Translation="10" />
    </Resource>
    <Resource Name="FontSize142" ID="93b4eecb-fe92-4e65-b925-1341edf797e0">
      <Localisation Language="en-GB" Translation="10" Default="True" />
      <Localisation Language="tr-TR" Translation="10" />
      <Localisation Language="it-IT" Translation="10" />
      <Localisation Language="es-ES" Translation="10" />
      <Localisation Language="pt-PT" Translation="10" />
      <Localisation Language="fr-CH" Translation="10" />
      <Localisation Language="de-DE" Translation="10" />
      <Localisation Language="ru-RU" Translation="10" />
      <Localisation Language="bg-BG" Translation="10" />
      <Localisation Language="sv-SE" Translation="10" />
    </Resource>
    <Resource Name="FontSize143" ID="087ed07f-135b-4908-8fe4-5f1c6dd2721c">
      <Localisation Language="en-GB" Translation="10" Default="True" />
      <Localisation Language="tr-TR" Translation="10" />
      <Localisation Language="it-IT" Translation="10" />
      <Localisation Language="es-ES" Translation="10" />
      <Localisation Language="pt-PT" Translation="10" />
      <Localisation Language="fr-CH" Translation="10" />
      <Localisation Language="de-DE" Translation="10" />
      <Localisation Language="ru-RU" Translation="10" />
      <Localisation Language="bg-BG" Translation="10" />
      <Localisation Language="sv-SE" Translation="10" />
    </Resource>
    <Resource Name="FontSize144" ID="691cc8c5-e58c-4d67-95b5-d8a7c036263d">
      <Localisation Language="en-GB" Translation="13" Default="True" />
      <Localisation Language="tr-TR" Translation="13" />
      <Localisation Language="it-IT" Translation="13" />
      <Localisation Language="es-ES" Translation="13" />
      <Localisation Language="pt-PT" Translation="13" />
      <Localisation Language="fr-CH" Translation="13" />
      <Localisation Language="de-DE" Translation="13" />
      <Localisation Language="ru-RU" Translation="13" />
      <Localisation Language="bg-BG" Translation="13" />
      <Localisation Language="sv-SE" Translation="13" />
    </Resource>
    <Resource Name="FontSize145" ID="9120e29c-6bca-4f96-8965-aa4ac0f7d241">
      <Localisation Language="en-GB" Translation="10" Default="True" />
      <Localisation Language="tr-TR" Translation="10" />
      <Localisation Language="it-IT" Translation="10" />
      <Localisation Language="es-ES" Translation="10" />
      <Localisation Language="pt-PT" Translation="10" />
      <Localisation Language="fr-CH" Translation="10" />
      <Localisation Language="de-DE" Translation="10" />
      <Localisation Language="ru-RU" Translation="10" />
      <Localisation Language="bg-BG" Translation="10" />
      <Localisation Language="sv-SE" Translation="10" />
    </Resource>
    <Resource Name="FontSize146" ID="ff236458-7152-4d6a-a555-d59314429ca9">
      <Localisation Language="en-GB" Translation="13" Default="True" />
      <Localisation Language="tr-TR" Translation="13" />
      <Localisation Language="it-IT" Translation="13" />
      <Localisation Language="es-ES" Translation="13" />
      <Localisation Language="pt-PT" Translation="13" />
      <Localisation Language="fr-CH" Translation="13" />
      <Localisation Language="de-DE" Translation="13" />
      <Localisation Language="ru-RU" Translation="13" />
      <Localisation Language="bg-BG" Translation="13" />
      <Localisation Language="sv-SE" Translation="13" />
    </Resource>
    <Resource Name="FontSize147" ID="98e7b812-74e8-49de-89d0-33e87abc662d">
      <Localisation Language="en-GB" Translation="9" Default="True" />
      <Localisation Language="tr-TR" Translation="9" />
      <Localisation Language="it-IT" Translation="9" />
      <Localisation Language="es-ES" Translation="9" />
      <Localisation Language="pt-PT" Translation="9" />
      <Localisation Language="fr-CH" Translation="9" />
      <Localisation Language="de-DE" Translation="9" />
      <Localisation Language="ru-RU" Translation="9" />
      <Localisation Language="bg-BG" Translation="9" />
      <Localisation Language="sv-SE" Translation="9" />
    </Resource>
    <Resource Name="FontSize148" ID="0715b325-5206-491d-af8e-9a313c9f5b7d">
      <Localisation Language="en-GB" Translation="13" Default="True" />
      <Localisation Language="tr-TR" Translation="13" />
      <Localisation Language="it-IT" Translation="13" />
      <Localisation Language="es-ES" Translation="13" />
      <Localisation Language="pt-PT" Translation="13" />
      <Localisation Language="fr-CH" Translation="13" />
      <Localisation Language="de-DE" Translation="13" />
      <Localisation Language="ru-RU" Translation="13" />
      <Localisation Language="bg-BG" Translation="13" />
      <Localisation Language="sv-SE" Translation="13" />
    </Resource>
    <Resource Name="FontSize149" ID="410c0a63-eff9-4560-b243-10aea87d8cd5">
      <Localisation Language="en-GB" Translation="9" Default="True" />
      <Localisation Language="tr-TR" Translation="9" />
      <Localisation Language="it-IT" Translation="9" />
      <Localisation Language="es-ES" Translation="9" />
      <Localisation Language="pt-PT" Translation="9" />
      <Localisation Language="fr-CH" Translation="9" />
      <Localisation Language="de-DE" Translation="9" />
      <Localisation Language="ru-RU" Translation="9" />
      <Localisation Language="bg-BG" Translation="9" />
      <Localisation Language="sv-SE" Translation="9" />
    </Resource>
    <Resource Name="FontSize150" ID="af15186d-8500-4bcf-9874-6161b6e732b3">
      <Localisation Language="en-GB" Translation="10" Default="True" />
      <Localisation Language="tr-TR" Translation="10" />
      <Localisation Language="it-IT" Translation="10" />
      <Localisation Language="es-ES" Translation="10" />
      <Localisation Language="pt-PT" Translation="10" />
      <Localisation Language="fr-CH" Translation="10" />
      <Localisation Language="de-DE" Translation="10" />
      <Localisation Language="ru-RU" Translation="10" />
      <Localisation Language="bg-BG" Translation="10" />
      <Localisation Language="sv-SE" Translation="10" />
    </Resource>
    <Resource Name="FontSize151" ID="1dfdacab-84bb-496a-914d-e33a18026de0">
      <Localisation Language="en-GB" Translation="10" Default="True" />
      <Localisation Language="tr-TR" Translation="10" />
      <Localisation Language="it-IT" Translation="10" />
      <Localisation Language="es-ES" Translation="10" />
      <Localisation Language="pt-PT" Translation="10" />
      <Localisation Language="fr-CH" Translation="10" />
      <Localisation Language="de-DE" Translation="10" />
      <Localisation Language="ru-RU" Translation="10" />
      <Localisation Language="bg-BG" Translation="10" />
      <Localisation Language="sv-SE" Translation="10" />
    </Resource>
    <Resource Name="FontSize152" ID="745c5ddf-047b-459a-aede-ae7d6d543e4c">
      <Localisation Language="en-GB" Translation="10" Default="True" />
      <Localisation Language="tr-TR" Translation="10" />
      <Localisation Language="it-IT" Translation="10" />
      <Localisation Language="es-ES" Translation="10" />
      <Localisation Language="pt-PT" Translation="10" />
      <Localisation Language="fr-CH" Translation="10" />
      <Localisation Language="de-DE" Translation="10" />
      <Localisation Language="ru-RU" Translation="10" />
      <Localisation Language="bg-BG" Translation="10" />
      <Localisation Language="sv-SE" Translation="10" />
    </Resource>
    <Resource Name="FontSize153" ID="1ac2b426-efc4-4747-b74c-76d87be49a2b">
      <Localisation Language="en-GB" Translation="10" Default="True" />
      <Localisation Language="tr-TR" Translation="10" />
      <Localisation Language="it-IT" Translation="10" />
      <Localisation Language="es-ES" Translation="10" />
      <Localisation Language="pt-PT" Translation="10" />
      <Localisation Language="fr-CH" Translation="10" />
      <Localisation Language="de-DE" Translation="10" />
      <Localisation Language="ru-RU" Translation="10" />
      <Localisation Language="bg-BG" Translation="10" />
      <Localisation Language="sv-SE" Translation="10" />
    </Resource>
    <Resource Name="FontSize154" ID="7bdf07a4-910c-47d0-a31c-1c6e311c6297">
      <Localisation Language="en-GB" Translation="10" Default="True" />
      <Localisation Language="tr-TR" Translation="10" />
      <Localisation Language="it-IT" Translation="10" />
      <Localisation Language="es-ES" Translation="10" />
      <Localisation Language="pt-PT" Translation="10" />
      <Localisation Language="fr-CH" Translation="10" />
      <Localisation Language="de-DE" Translation="10" />
      <Localisation Language="ru-RU" Translation="10" />
      <Localisation Language="bg-BG" Translation="10" />
      <Localisation Language="sv-SE" Translation="10" />
    </Resource>
    <Resource Name="FontSize155" ID="1375b3d9-3fbe-40ed-a0d8-baabc3b4543b">
      <Localisation Language="en-GB" Translation="10" Default="True" />
      <Localisation Language="tr-TR" Translation="10" />
      <Localisation Language="it-IT" Translation="10" />
      <Localisation Language="es-ES" Translation="10" />
      <Localisation Language="pt-PT" Translation="10" />
      <Localisation Language="fr-CH" Translation="10" />
      <Localisation Language="de-DE" Translation="10" />
      <Localisation Language="ru-RU" Translation="10" />
      <Localisation Language="bg-BG" Translation="10" />
      <Localisation Language="sv-SE" Translation="10" />
    </Resource>
    <Resource Name="FontSize156" ID="237e4e2f-b7a0-4906-9ce3-cf38c7559e95">
      <Localisation Language="en-GB" Translation="10" Default="True" />
      <Localisation Language="tr-TR" Translation="10" />
      <Localisation Language="it-IT" Translation="10" />
      <Localisation Language="es-ES" Translation="10" />
      <Localisation Language="pt-PT" Translation="10" />
      <Localisation Language="fr-CH" Translation="10" />
      <Localisation Language="de-DE" Translation="10" />
      <Localisation Language="ru-RU" Translation="10" />
      <Localisation Language="bg-BG" Translation="10" />
      <Localisation Language="sv-SE" Translation="10" />
    </Resource>
    <Resource Name="FontSize157" ID="40e9e4ce-f837-48e7-9f47-39f8dcfb228d">
      <Localisation Language="en-GB" Translation="10" Default="True" />
      <Localisation Language="tr-TR" Translation="10" />
      <Localisation Language="it-IT" Translation="10" />
      <Localisation Language="es-ES" Translation="10" />
      <Localisation Language="pt-PT" Translation="10" />
      <Localisation Language="fr-CH" Translation="10" />
      <Localisation Language="de-DE" Translation="10" />
      <Localisation Language="ru-RU" Translation="10" />
      <Localisation Language="bg-BG" Translation="10" />
      <Localisation Language="sv-SE" Translation="10" />
    </Resource>
    <Resource Name="FontSize158" ID="6bc773ae-1cd5-4859-b72a-977fc0438878">
      <Localisation Language="en-GB" Translation="10" Default="True" />
      <Localisation Language="tr-TR" Translation="10" />
      <Localisation Language="it-IT" Translation="10" />
      <Localisation Language="es-ES" Translation="10" />
      <Localisation Language="pt-PT" Translation="10" />
      <Localisation Language="fr-CH" Translation="10" />
      <Localisation Language="de-DE" Translation="10" />
      <Localisation Language="ru-RU" Translation="10" />
      <Localisation Language="bg-BG" Translation="10" />
      <Localisation Language="sv-SE" Translation="10" />
    </Resource>
    <Resource Name="FontSize159" ID="4df94426-f56b-4fac-b7da-0abaead6964e">
      <Localisation Language="en-GB" Translation="10" Default="True" />
      <Localisation Language="tr-TR" Translation="10" />
      <Localisation Language="it-IT" Translation="10" />
      <Localisation Language="es-ES" Translation="10" />
      <Localisation Language="pt-PT" Translation="10" />
      <Localisation Language="fr-CH" Translation="10" />
      <Localisation Language="de-DE" Translation="10" />
      <Localisation Language="ru-RU" Translation="10" />
      <Localisation Language="bg-BG" Translation="10" />
      <Localisation Language="sv-SE" Translation="10" />
    </Resource>
    <Resource Name="FontSize160" ID="3a5a0715-01d3-4b38-b220-6a81680a9943">
      <Localisation Language="en-GB" Translation="10" Default="True" />
      <Localisation Language="tr-TR" Translation="10" />
      <Localisation Language="it-IT" Translation="10" />
      <Localisation Language="es-ES" Translation="10" />
      <Localisation Language="pt-PT" Translation="10" />
      <Localisation Language="fr-CH" Translation="10" />
      <Localisation Language="de-DE" Translation="10" />
      <Localisation Language="ru-RU" Translation="10" />
      <Localisation Language="bg-BG" Translation="10" />
      <Localisation Language="sv-SE" Translation="10" />
    </Resource>
    <Resource Name="FontSize161" ID="a4b852a6-9d2f-437d-9364-2d28f1f09fe8">
      <Localisation Language="en-GB" Translation="10" Default="True" />
      <Localisation Language="tr-TR" Translation="10" />
      <Localisation Language="it-IT" Translation="10" />
      <Localisation Language="es-ES" Translation="10" />
      <Localisation Language="pt-PT" Translation="10" />
      <Localisation Language="fr-CH" Translation="10" />
      <Localisation Language="de-DE" Translation="10" />
      <Localisation Language="ru-RU" Translation="10" />
      <Localisation Language="bg-BG" Translation="10" />
      <Localisation Language="sv-SE" Translation="10" />
    </Resource>
    <Resource Name="FontSize162" ID="16fa7757-47ed-4508-91a7-c352cee9e909">
      <Localisation Language="en-GB" Translation="10" Default="True" />
      <Localisation Language="tr-TR" Translation="10" />
      <Localisation Language="it-IT" Translation="10" />
      <Localisation Language="es-ES" Translation="10" />
      <Localisation Language="pt-PT" Translation="10" />
      <Localisation Language="fr-CH" Translation="10" />
      <Localisation Language="de-DE" Translation="10" />
      <Localisation Language="ru-RU" Translation="10" />
      <Localisation Language="bg-BG" Translation="10" />
      <Localisation Language="sv-SE" Translation="10" />
    </Resource>
    <Resource Name="FontSize163" ID="c4967eea-cf1c-4d72-864b-e9dea1c7e125">
      <Localisation Language="en-GB" Translation="10" Default="True" />
      <Localisation Language="tr-TR" Translation="10" />
      <Localisation Language="it-IT" Translation="10" />
      <Localisation Language="es-ES" Translation="10" />
      <Localisation Language="pt-PT" Translation="10" />
      <Localisation Language="fr-CH" Translation="10" />
      <Localisation Language="de-DE" Translation="10" />
      <Localisation Language="ru-RU" Translation="10" />
      <Localisation Language="bg-BG" Translation="10" />
      <Localisation Language="sv-SE" Translation="10" />
    </Resource>
    <Resource Name="FontSize164" ID="9e29a55e-444f-4992-8c52-5a2e2109d1f9">
      <Localisation Language="en-GB" Translation="10" Default="True" />
      <Localisation Language="tr-TR" Translation="10" />
      <Localisation Language="it-IT" Translation="10" />
      <Localisation Language="es-ES" Translation="10" />
      <Localisation Language="pt-PT" Translation="10" />
      <Localisation Language="fr-CH" Translation="10" />
      <Localisation Language="de-DE" Translation="10" />
      <Localisation Language="ru-RU" Translation="10" />
      <Localisation Language="bg-BG" Translation="10" />
      <Localisation Language="sv-SE" Translation="10" />
    </Resource>
    <Resource Name="FontSize165" ID="d94cd1dd-2a0d-4f9c-9b47-9c9f00fbb84e">
      <Localisation Language="en-GB" Translation="20" Default="True" />
      <Localisation Language="tr-TR" Translation="20" />
      <Localisation Language="it-IT" Translation="20" />
      <Localisation Language="es-ES" Translation="20" />
      <Localisation Language="pt-PT" Translation="20" />
      <Localisation Language="fr-CH" Translation="20" />
      <Localisation Language="de-DE" Translation="20" />
      <Localisation Language="ru-RU" Translation="20" />
      <Localisation Language="bg-BG" Translation="20" />
      <Localisation Language="sv-SE" Translation="20" />
    </Resource>
    <Resource Name="FontSize166" ID="15212a95-9afd-4582-9163-5bb343eeef68">
      <Localisation Language="en-GB" Translation="10" Default="True" />
      <Localisation Language="tr-TR" Translation="10" />
      <Localisation Language="it-IT" Translation="10" />
      <Localisation Language="es-ES" Translation="10" />
      <Localisation Language="pt-PT" Translation="10" />
      <Localisation Language="fr-CH" Translation="10" />
      <Localisation Language="de-DE" Translation="10" />
      <Localisation Language="ru-RU" Translation="10" />
      <Localisation Language="bg-BG" Translation="10" />
      <Localisation Language="sv-SE" Translation="10" />
    </Resource>
    <Resource Name="FontSize167" ID="383bfa58-302a-42b3-ae00-d040e1d4c631">
      <Localisation Language="en-GB" Translation="10" Default="True" />
      <Localisation Language="tr-TR" Translation="10" />
      <Localisation Language="it-IT" Translation="10" />
      <Localisation Language="es-ES" Translation="10" />
      <Localisation Language="pt-PT" Translation="10" />
      <Localisation Language="fr-CH" Translation="10" />
      <Localisation Language="de-DE" Translation="10" />
      <Localisation Language="ru-RU" Translation="10" />
      <Localisation Language="bg-BG" Translation="10" />
      <Localisation Language="sv-SE" Translation="10" />
    </Resource>
    <Resource Name="FontSize168" ID="d526091a-482e-46ad-9d84-e581fd085804">
      <Localisation Language="en-GB" Translation="10" Default="True" />
      <Localisation Language="tr-TR" Translation="10" />
      <Localisation Language="it-IT" Translation="10" />
      <Localisation Language="es-ES" Translation="10" />
      <Localisation Language="pt-PT" Translation="10" />
      <Localisation Language="fr-CH" Translation="10" />
      <Localisation Language="de-DE" Translation="10" />
      <Localisation Language="ru-RU" Translation="10" />
      <Localisation Language="bg-BG" Translation="10" />
      <Localisation Language="sv-SE" Translation="10" />
    </Resource>
    <Resource Name="FontSize169" ID="2a046920-1bcb-4ca4-88b0-3baf05b36836">
      <Localisation Language="en-GB" Translation="10" Default="True" />
      <Localisation Language="tr-TR" Translation="10" />
      <Localisation Language="it-IT" Translation="10" />
      <Localisation Language="es-ES" Translation="10" />
      <Localisation Language="pt-PT" Translation="10" />
      <Localisation Language="fr-CH" Translation="10" />
      <Localisation Language="de-DE" Translation="10" />
      <Localisation Language="ru-RU" Translation="10" />
      <Localisation Language="bg-BG" Translation="10" />
      <Localisation Language="sv-SE" Translation="10" />
    </Resource>
    <Resource Name="FontSize170" ID="8af0a907-dde0-45fb-8b46-87d00b0f6fe7">
      <Localisation Language="en-GB" Translation="10" Default="True" />
      <Localisation Language="tr-TR" Translation="10" />
      <Localisation Language="it-IT" Translation="10" />
      <Localisation Language="es-ES" Translation="10" />
      <Localisation Language="pt-PT" Translation="10" />
      <Localisation Language="fr-CH" Translation="10" />
      <Localisation Language="de-DE" Translation="10" />
      <Localisation Language="ru-RU" Translation="10" />
      <Localisation Language="bg-BG" Translation="10" />
      <Localisation Language="sv-SE" Translation="10" />
    </Resource>
  </Resources>
  <Resources Type="FontFamilies">
    <Resource Name="FontFamily" ID="8c7569fd-210a-4771-a23b-3f212aa081d0">
      <Localisation Language="en-GB" Translation="Segoe UI" Default="True" />
      <Localisation Language="tr-TR" Translation="Segoe UI" />
      <Localisation Language="it-IT" Translation="Segoe UI" />
      <Localisation Language="es-ES" Translation="Segoe UI" />
      <Localisation Language="pt-PT" Translation="Segoe UI" />
      <Localisation Language="fr-CH" Translation="Segoe UI" />
      <Localisation Language="de-DE" Translation="Segoe UI" />
      <Localisation Language="ru-RU" Translation="Segoe UI" />
      <Localisation Language="bg-BG" Translation="Segoe UI" />
      <Localisation Language="sv-SE" Translation="Segoe UI" />
    </Resource>
  </Resources>
  <Resources Type="FontStyles">
    <Resource Name="FontStyle" ID="2303fc64-a94f-4f2e-83fc-cce5168a85ea">
      <Localisation Language="en-GB" Translation="Normal" Default="True" />
      <Localisation Language="tr-TR" Translation="Normal" />
      <Localisation Language="it-IT" Translation="Normal" />
      <Localisation Language="es-ES" Translation="Normal" />
      <Localisation Language="pt-PT" Translation="Normal" />
      <Localisation Language="fr-CH" Translation="Normal" />
      <Localisation Language="de-DE" Translation="Normal" />
      <Localisation Language="ru-RU" Translation="Normal" />
      <Localisation Language="bg-BG" Translation="Normal" />
      <Localisation Language="sv-SE" Translation="Normal" />
    </Resource>
    <Resource Name="FontStyle62" ID="12d8bf10-f57d-421c-ac1e-4c04233d21cb">
      <Localisation Language="en-GB" Translation="BoldItalic" Default="True" />
      <Localisation Language="tr-TR" Translation="BoldItalic" />
      <Localisation Language="it-IT" Translation="BoldItalic" />
      <Localisation Language="es-ES" Translation="BoldItalic" />
      <Localisation Language="pt-PT" Translation="BoldItalic" />
      <Localisation Language="fr-CH" Translation="BoldItalic" />
      <Localisation Language="de-DE" Translation="BoldItalic" />
      <Localisation Language="ru-RU" Translation="BoldItalic" />
      <Localisation Language="bg-BG" Translation="BoldItalic" />
      <Localisation Language="sv-SE" Translation="BoldItalic" />
    </Resource>
    <Resource Name="FontStyle63" ID="3fe76687-74ed-4567-9173-9f5442366698">
      <Localisation Language="en-GB" Translation="Bold" Default="True" />
      <Localisation Language="tr-TR" Translation="Bold" />
      <Localisation Language="it-IT" Translation="Bold" />
      <Localisation Language="es-ES" Translation="Bold" />
      <Localisation Language="pt-PT" Translation="Bold" />
      <Localisation Language="fr-CH" Translation="Bold" />
      <Localisation Language="de-DE" Translation="Bold" />
      <Localisation Language="ru-RU" Translation="Bold" />
      <Localisation Language="bg-BG" Translation="Bold" />
      <Localisation Language="sv-SE" Translation="Bold" />
    </Resource>
    <Resource Name="FontStyle64" ID="5396c5e4-d028-4cfe-a357-2187fe770087">
      <Localisation Language="en-GB" Translation="Bold" Default="True" />
      <Localisation Language="tr-TR" Translation="Bold" />
      <Localisation Language="it-IT" Translation="Bold" />
      <Localisation Language="es-ES" Translation="Bold" />
      <Localisation Language="pt-PT" Translation="Bold" />
      <Localisation Language="fr-CH" Translation="Bold" />
      <Localisation Language="de-DE" Translation="Bold" />
      <Localisation Language="ru-RU" Translation="Bold" />
      <Localisation Language="bg-BG" Translation="Bold" />
      <Localisation Language="sv-SE" Translation="Bold" />
    </Resource>
    <Resource Name="FontStyle65" ID="1f91f53a-b646-4727-a8f9-7ee4161f589a">
      <Localisation Language="en-GB" Translation="Bold" Default="True" />
      <Localisation Language="tr-TR" Translation="Bold" />
      <Localisation Language="it-IT" Translation="Bold" />
      <Localisation Language="es-ES" Translation="Bold" />
      <Localisation Language="pt-PT" Translation="Bold" />
      <Localisation Language="fr-CH" Translation="Bold" />
      <Localisation Language="de-DE" Translation="Bold" />
      <Localisation Language="ru-RU" Translation="Bold" />
      <Localisation Language="bg-BG" Translation="Bold" />
      <Localisation Language="sv-SE" Translation="Bold" />
    </Resource>
    <Resource Name="FontStyle66" ID="997e21e0-6e25-43a6-8e78-435f32324b5f">
      <Localisation Language="en-GB" Translation="Bold" Default="True" />
      <Localisation Language="tr-TR" Translation="Bold" />
      <Localisation Language="it-IT" Translation="Bold" />
      <Localisation Language="es-ES" Translation="Bold" />
      <Localisation Language="pt-PT" Translation="Bold" />
      <Localisation Language="fr-CH" Translation="Bold" />
      <Localisation Language="de-DE" Translation="Bold" />
      <Localisation Language="ru-RU" Translation="Bold" />
      <Localisation Language="bg-BG" Translation="Bold" />
      <Localisation Language="sv-SE" Translation="Bold" />
    </Resource>
    <Resource Name="FontStyle67" ID="2523950c-9e30-4058-8e1f-248b50704826">
      <Localisation Language="en-GB" Translation="Bold" Default="True" />
      <Localisation Language="tr-TR" Translation="Bold" />
      <Localisation Language="it-IT" Translation="Bold" />
      <Localisation Language="es-ES" Translation="Bold" />
      <Localisation Language="pt-PT" Translation="Bold" />
      <Localisation Language="fr-CH" Translation="Bold" />
      <Localisation Language="de-DE" Translation="Bold" />
      <Localisation Language="ru-RU" Translation="Bold" />
      <Localisation Language="bg-BG" Translation="Bold" />
      <Localisation Language="sv-SE" Translation="Bold" />
    </Resource>
    <Resource Name="FontStyle68" ID="3ce5e2f2-0496-4c03-90ab-a7d71d702456">
      <Localisation Language="en-GB" Translation="Bold" Default="True" />
      <Localisation Language="tr-TR" Translation="Bold" />
      <Localisation Language="it-IT" Translation="Bold" />
      <Localisation Language="es-ES" Translation="Bold" />
      <Localisation Language="pt-PT" Translation="Bold" />
      <Localisation Language="fr-CH" Translation="Bold" />
      <Localisation Language="de-DE" Translation="Bold" />
      <Localisation Language="ru-RU" Translation="Bold" />
      <Localisation Language="bg-BG" Translation="Bold" />
      <Localisation Language="sv-SE" Translation="Bold" />
    </Resource>
    <Resource Name="FontStyle69" ID="01b803a2-a8cd-45dd-a3f6-e7a6e9503978">
      <Localisation Language="en-GB" Translation="Bold" Default="True" />
      <Localisation Language="tr-TR" Translation="Bold" />
      <Localisation Language="it-IT" Translation="Bold" />
      <Localisation Language="es-ES" Translation="Bold" />
      <Localisation Language="pt-PT" Translation="Bold" />
      <Localisation Language="fr-CH" Translation="Bold" />
      <Localisation Language="de-DE" Translation="Bold" />
      <Localisation Language="ru-RU" Translation="Bold" />
      <Localisation Language="bg-BG" Translation="Bold" />
      <Localisation Language="sv-SE" Translation="Bold" />
    </Resource>
    <Resource Name="FontStyle70" ID="4958dece-02a8-4e40-a2f9-384542b317fb">
      <Localisation Language="en-GB" Translation="Bold" Default="True" />
      <Localisation Language="tr-TR" Translation="Bold" />
      <Localisation Language="it-IT" Translation="Bold" />
      <Localisation Language="es-ES" Translation="Bold" />
      <Localisation Language="pt-PT" Translation="Bold" />
      <Localisation Language="fr-CH" Translation="Bold" />
      <Localisation Language="de-DE" Translation="Bold" />
      <Localisation Language="ru-RU" Translation="Bold" />
      <Localisation Language="bg-BG" Translation="Bold" />
      <Localisation Language="sv-SE" Translation="Normal" />
    </Resource>
    <Resource Name="FontStyle71" ID="337e8be9-5542-476b-ba32-7e5687f90737">
      <Localisation Language="en-GB" Translation="Bold" Default="True" />
      <Localisation Language="tr-TR" Translation="Bold" />
      <Localisation Language="it-IT" Translation="Bold" />
      <Localisation Language="es-ES" Translation="Bold" />
      <Localisation Language="pt-PT" Translation="Bold" />
      <Localisation Language="fr-CH" Translation="Bold" />
      <Localisation Language="de-DE" Translation="Bold" />
      <Localisation Language="ru-RU" Translation="Bold" />
      <Localisation Language="bg-BG" Translation="Bold" />
      <Localisation Language="sv-SE" Translation="Bold" />
    </Resource>
    <Resource Name="FontStyle72" ID="46d11a87-036c-4dcd-883d-4697c4656905">
      <Localisation Language="en-GB" Translation="Bold" Default="True" />
      <Localisation Language="tr-TR" Translation="Bold" />
      <Localisation Language="it-IT" Translation="Bold" />
      <Localisation Language="es-ES" Translation="Bold" />
      <Localisation Language="pt-PT" Translation="Bold" />
      <Localisation Language="fr-CH" Translation="Bold" />
      <Localisation Language="de-DE" Translation="Bold" />
      <Localisation Language="ru-RU" Translation="Bold" />
      <Localisation Language="bg-BG" Translation="Bold" />
      <Localisation Language="sv-SE" Translation="Bold" />
    </Resource>
    <Resource Name="FontStyle73" ID="ae4c2bc6-5f33-444e-9e10-005d117d2858">
      <Localisation Language="en-GB" Translation="Bold" Default="True" />
      <Localisation Language="tr-TR" Translation="Bold" />
      <Localisation Language="it-IT" Translation="Bold" />
      <Localisation Language="es-ES" Translation="Bold" />
      <Localisation Language="pt-PT" Translation="Bold" />
      <Localisation Language="fr-CH" Translation="Bold" />
      <Localisation Language="de-DE" Translation="Bold" />
      <Localisation Language="ru-RU" Translation="Bold" />
      <Localisation Language="bg-BG" Translation="Bold" />
      <Localisation Language="sv-SE" Translation="Bold" />
    </Resource>
    <Resource Name="FontStyle74" ID="728934de-48b0-4143-9ffd-df34c57a0b34">
      <Localisation Language="en-GB" Translation="Bold" Default="True" />
      <Localisation Language="tr-TR" Translation="Bold" />
      <Localisation Language="it-IT" Translation="Bold" />
      <Localisation Language="es-ES" Translation="Bold" />
      <Localisation Language="pt-PT" Translation="Bold" />
      <Localisation Language="fr-CH" Translation="Bold" />
      <Localisation Language="de-DE" Translation="Bold" />
      <Localisation Language="ru-RU" Translation="Bold" />
      <Localisation Language="bg-BG" Translation="Bold" />
      <Localisation Language="sv-SE" Translation="Bold" />
    </Resource>
    <Resource Name="FontStyle75" ID="2e119cc4-2171-468c-9640-09213a186638">
      <Localisation Language="en-GB" Translation="Bold" Default="True" />
      <Localisation Language="tr-TR" Translation="Bold" />
      <Localisation Language="it-IT" Translation="Bold" />
      <Localisation Language="es-ES" Translation="Bold" />
      <Localisation Language="pt-PT" Translation="Bold" />
      <Localisation Language="fr-CH" Translation="Bold" />
      <Localisation Language="de-DE" Translation="Bold" />
      <Localisation Language="ru-RU" Translation="Bold" />
      <Localisation Language="bg-BG" Translation="Bold" />
      <Localisation Language="sv-SE" Translation="Bold" />
    </Resource>
    <Resource Name="FontStyle76" ID="043a5083-f3c6-44f2-ab43-ba68ff516673">
      <Localisation Language="en-GB" Translation="Bold" Default="True" />
      <Localisation Language="tr-TR" Translation="Bold" />
      <Localisation Language="it-IT" Translation="Bold" />
      <Localisation Language="es-ES" Translation="Bold" />
      <Localisation Language="pt-PT" Translation="Bold" />
      <Localisation Language="fr-CH" Translation="Bold" />
      <Localisation Language="de-DE" Translation="Bold" />
      <Localisation Language="ru-RU" Translation="Bold" />
      <Localisation Language="bg-BG" Translation="Bold" />
      <Localisation Language="sv-SE" Translation="Bold" />
    </Resource>
    <Resource Name="FontStyle77" ID="92fc055d-db9f-4bc2-ad1c-7ceb3c020f92">
      <Localisation Language="en-GB" Translation="Bold" Default="True" />
      <Localisation Language="tr-TR" Translation="Bold" />
      <Localisation Language="it-IT" Translation="Bold" />
      <Localisation Language="es-ES" Translation="Bold" />
      <Localisation Language="pt-PT" Translation="Bold" />
      <Localisation Language="fr-CH" Translation="Bold" />
      <Localisation Language="de-DE" Translation="Bold" />
      <Localisation Language="ru-RU" Translation="Bold" />
      <Localisation Language="bg-BG" Translation="Bold" />
      <Localisation Language="sv-SE" Translation="Bold" />
    </Resource>
    <Resource Name="FontStyle78" ID="85100fc3-bb20-4e53-b172-ac91015a2618">
      <Localisation Language="en-GB" Translation="Bold" Default="True" />
      <Localisation Language="tr-TR" Translation="Bold" />
      <Localisation Language="it-IT" Translation="Bold" />
      <Localisation Language="es-ES" Translation="Bold" />
      <Localisation Language="pt-PT" Translation="Bold" />
      <Localisation Language="fr-CH" Translation="Bold" />
      <Localisation Language="de-DE" Translation="Bold" />
      <Localisation Language="ru-RU" Translation="Bold" />
      <Localisation Language="bg-BG" Translation="Bold" />
      <Localisation Language="sv-SE" Translation="Bold" />
    </Resource>
    <Resource Name="FontStyle79" ID="6625e644-ce16-48f9-9b6c-6c1bd96b0ca6">
      <Localisation Language="en-GB" Translation="Bold" Default="True" />
      <Localisation Language="tr-TR" Translation="Bold" />
      <Localisation Language="it-IT" Translation="Bold" />
      <Localisation Language="es-ES" Translation="Bold" />
      <Localisation Language="pt-PT" Translation="Bold" />
      <Localisation Language="fr-CH" Translation="Bold" />
      <Localisation Language="de-DE" Translation="Bold" />
      <Localisation Language="ru-RU" Translation="Bold" />
      <Localisation Language="bg-BG" Translation="Bold" />
      <Localisation Language="sv-SE" Translation="Bold" />
    </Resource>
    <Resource Name="FontStyle80" ID="16bffab1-509d-4a6c-b924-eddf071ce848">
      <Localisation Language="en-GB" Translation="Bold" Default="True" />
      <Localisation Language="tr-TR" Translation="Bold" />
      <Localisation Language="it-IT" Translation="Bold" />
      <Localisation Language="es-ES" Translation="Bold" />
      <Localisation Language="pt-PT" Translation="Bold" />
      <Localisation Language="fr-CH" Translation="Bold" />
      <Localisation Language="de-DE" Translation="Bold" />
      <Localisation Language="ru-RU" Translation="Bold" />
      <Localisation Language="bg-BG" Translation="Bold" />
      <Localisation Language="sv-SE" Translation="Bold" />
    </Resource>
    <Resource Name="FontStyle81" ID="f2137195-aede-43c4-a5d5-2232362a967e">
      <Localisation Language="en-GB" Translation="Bold" Default="True" />
      <Localisation Language="tr-TR" Translation="Bold" />
      <Localisation Language="it-IT" Translation="Bold" />
      <Localisation Language="es-ES" Translation="Bold" />
      <Localisation Language="pt-PT" Translation="Bold" />
      <Localisation Language="fr-CH" Translation="Bold" />
      <Localisation Language="de-DE" Translation="Bold" />
      <Localisation Language="ru-RU" Translation="Bold" />
      <Localisation Language="bg-BG" Translation="Bold" />
      <Localisation Language="sv-SE" Translation="Bold" />
    </Resource>
    <Resource Name="FontStyle82" ID="2e3e0628-2551-485b-8e64-94fbcd84b484">
      <Localisation Language="en-GB" Translation="Bold" Default="True" />
      <Localisation Language="tr-TR" Translation="Bold" />
      <Localisation Language="it-IT" Translation="Bold" />
      <Localisation Language="es-ES" Translation="Bold" />
      <Localisation Language="pt-PT" Translation="Bold" />
      <Localisation Language="fr-CH" Translation="Bold" />
      <Localisation Language="de-DE" Translation="Bold" />
      <Localisation Language="ru-RU" Translation="Bold" />
      <Localisation Language="bg-BG" Translation="Bold" />
      <Localisation Language="sv-SE" Translation="Bold" />
    </Resource>
    <Resource Name="FontStyle83" ID="739ad014-3b67-4d54-9175-1db6b4503bce">
      <Localisation Language="en-GB" Translation="Bold" Default="True" />
      <Localisation Language="tr-TR" Translation="Bold" />
      <Localisation Language="it-IT" Translation="Bold" />
      <Localisation Language="es-ES" Translation="Bold" />
      <Localisation Language="pt-PT" Translation="Bold" />
      <Localisation Language="fr-CH" Translation="Bold" />
      <Localisation Language="de-DE" Translation="Bold" />
      <Localisation Language="ru-RU" Translation="Bold" />
      <Localisation Language="bg-BG" Translation="Bold" />
      <Localisation Language="sv-SE" Translation="Bold" />
    </Resource>
    <Resource Name="FontStyle84" ID="2fd578b0-eb4c-4276-8098-4957108f2c7d">
      <Localisation Language="en-GB" Translation="Bold" Default="True" />
      <Localisation Language="tr-TR" Translation="Bold" />
      <Localisation Language="it-IT" Translation="Bold" />
      <Localisation Language="es-ES" Translation="Bold" />
      <Localisation Language="pt-PT" Translation="Bold" />
      <Localisation Language="fr-CH" Translation="Bold" />
      <Localisation Language="de-DE" Translation="Bold" />
      <Localisation Language="ru-RU" Translation="Bold" />
      <Localisation Language="bg-BG" Translation="Bold" />
      <Localisation Language="sv-SE" Translation="Bold" />
    </Resource>
    <Resource Name="FontStyle85" ID="a975ec5d-4157-4b38-9a6e-b8f65dd21509">
      <Localisation Language="en-GB" Translation="Bold" Default="True" />
      <Localisation Language="tr-TR" Translation="Bold" />
      <Localisation Language="it-IT" Translation="Bold" />
      <Localisation Language="es-ES" Translation="Bold" />
      <Localisation Language="pt-PT" Translation="Bold" />
      <Localisation Language="fr-CH" Translation="Bold" />
      <Localisation Language="de-DE" Translation="Bold" />
      <Localisation Language="ru-RU" Translation="Bold" />
      <Localisation Language="bg-BG" Translation="Bold" />
      <Localisation Language="sv-SE" Translation="Bold" />
    </Resource>
    <Resource Name="FontStyle86" ID="30715eb5-20d0-4ec1-b838-90ced4bed07e">
      <Localisation Language="en-GB" Translation="Bold" Default="True" />
      <Localisation Language="tr-TR" Translation="Bold" />
      <Localisation Language="it-IT" Translation="Bold" />
      <Localisation Language="es-ES" Translation="Bold" />
      <Localisation Language="pt-PT" Translation="Bold" />
      <Localisation Language="fr-CH" Translation="Bold" />
      <Localisation Language="de-DE" Translation="Bold" />
      <Localisation Language="ru-RU" Translation="Bold" />
      <Localisation Language="bg-BG" Translation="Bold" />
      <Localisation Language="sv-SE" Translation="Bold" />
    </Resource>
    <Resource Name="FontStyle87" ID="8d234946-f5f3-4e6b-b6ea-4ca8ce73d496">
      <Localisation Language="en-GB" Translation="Bold" Default="True" />
      <Localisation Language="tr-TR" Translation="Bold" />
      <Localisation Language="it-IT" Translation="Bold" />
      <Localisation Language="es-ES" Translation="Bold" />
      <Localisation Language="pt-PT" Translation="Bold" />
      <Localisation Language="fr-CH" Translation="Bold" />
      <Localisation Language="de-DE" Translation="Bold" />
      <Localisation Language="ru-RU" Translation="Bold" />
      <Localisation Language="bg-BG" Translation="Bold" />
      <Localisation Language="sv-SE" Translation="Bold" />
    </Resource>
    <Resource Name="FontStyle88" ID="2b674cd7-a9ce-45cf-b2c4-8e67db9d31d2">
      <Localisation Language="en-GB" Translation="Bold" Default="True" />
      <Localisation Language="tr-TR" Translation="Bold" />
      <Localisation Language="it-IT" Translation="Bold" />
      <Localisation Language="es-ES" Translation="Bold" />
      <Localisation Language="pt-PT" Translation="Bold" />
      <Localisation Language="fr-CH" Translation="Bold" />
      <Localisation Language="de-DE" Translation="Bold" />
      <Localisation Language="ru-RU" Translation="Bold" />
      <Localisation Language="bg-BG" Translation="Bold" />
      <Localisation Language="sv-SE" Translation="Bold" />
    </Resource>
    <Resource Name="FontStyle89" ID="c4e09746-9278-4aef-8d72-ed1ba3ec8a18">
      <Localisation Language="en-GB" Translation="Bold" Default="True" />
      <Localisation Language="tr-TR" Translation="Bold" />
      <Localisation Language="it-IT" Translation="Bold" />
      <Localisation Language="es-ES" Translation="Bold" />
      <Localisation Language="pt-PT" Translation="Bold" />
      <Localisation Language="fr-CH" Translation="Bold" />
      <Localisation Language="de-DE" Translation="Bold" />
      <Localisation Language="ru-RU" Translation="Bold" />
      <Localisation Language="bg-BG" Translation="Bold" />
      <Localisation Language="sv-SE" Translation="Bold" />
    </Resource>
    <Resource Name="FontStyle90" ID="1273f26f-398e-41bf-a3a7-5b88fc36e178">
      <Localisation Language="en-GB" Translation="Bold" Default="True" />
      <Localisation Language="tr-TR" Translation="Bold" />
      <Localisation Language="it-IT" Translation="Bold" />
      <Localisation Language="es-ES" Translation="Bold" />
      <Localisation Language="pt-PT" Translation="Bold" />
      <Localisation Language="fr-CH" Translation="Bold" />
      <Localisation Language="de-DE" Translation="Bold" />
      <Localisation Language="ru-RU" Translation="Bold" />
      <Localisation Language="bg-BG" Translation="Bold" />
      <Localisation Language="sv-SE" Translation="Bold" />
    </Resource>
    <Resource Name="FontStyle91" ID="39835059-438f-4ef1-883f-70cab983562e">
      <Localisation Language="en-GB" Translation="Bold" Default="True" />
      <Localisation Language="tr-TR" Translation="Bold" />
      <Localisation Language="it-IT" Translation="Bold" />
      <Localisation Language="es-ES" Translation="Bold" />
      <Localisation Language="pt-PT" Translation="Bold" />
      <Localisation Language="fr-CH" Translation="Bold" />
      <Localisation Language="de-DE" Translation="Bold" />
      <Localisation Language="ru-RU" Translation="Bold" />
      <Localisation Language="bg-BG" Translation="Bold" />
      <Localisation Language="sv-SE" Translation="Bold" />
    </Resource>
    <Resource Name="FontStyle92" ID="be6827d9-a40f-46a7-b346-f1dc30db61e9">
      <Localisation Language="en-GB" Translation="Bold" Default="True" />
      <Localisation Language="tr-TR" Translation="Bold" />
      <Localisation Language="it-IT" Translation="Bold" />
      <Localisation Language="es-ES" Translation="Bold" />
      <Localisation Language="pt-PT" Translation="Bold" />
      <Localisation Language="fr-CH" Translation="Bold" />
      <Localisation Language="de-DE" Translation="Bold" />
      <Localisation Language="ru-RU" Translation="Bold" />
      <Localisation Language="bg-BG" Translation="Bold" />
      <Localisation Language="sv-SE" Translation="Bold" />
    </Resource>
    <Resource Name="FontStyle93" ID="22b2a563-c29b-4ab0-ac3d-f3d3b57e0c22">
      <Localisation Language="en-GB" Translation="Bold" Default="True" />
      <Localisation Language="tr-TR" Translation="Bold" />
      <Localisation Language="it-IT" Translation="Bold" />
      <Localisation Language="es-ES" Translation="Bold" />
      <Localisation Language="pt-PT" Translation="Bold" />
      <Localisation Language="fr-CH" Translation="Bold" />
      <Localisation Language="de-DE" Translation="Bold" />
      <Localisation Language="ru-RU" Translation="Bold" />
      <Localisation Language="bg-BG" Translation="Bold" />
      <Localisation Language="sv-SE" Translation="Bold" />
    </Resource>
    <Resource Name="FontStyle94" ID="4c257565-579a-42b2-861b-231cfdc8794a">
      <Localisation Language="en-GB" Translation="Bold" Default="True" />
      <Localisation Language="tr-TR" Translation="Bold" />
      <Localisation Language="it-IT" Translation="Bold" />
      <Localisation Language="es-ES" Translation="Bold" />
      <Localisation Language="pt-PT" Translation="Bold" />
      <Localisation Language="fr-CH" Translation="Bold" />
      <Localisation Language="de-DE" Translation="Bold" />
      <Localisation Language="ru-RU" Translation="Bold" />
      <Localisation Language="bg-BG" Translation="Bold" />
      <Localisation Language="sv-SE" Translation="Bold" />
    </Resource>
    <Resource Name="FontStyle95" ID="ffcf8168-3dad-4104-9b35-db72940d5cad">
      <Localisation Language="en-GB" Translation="Bold" Default="True" />
      <Localisation Language="tr-TR" Translation="Bold" />
      <Localisation Language="it-IT" Translation="Bold" />
      <Localisation Language="es-ES" Translation="Bold" />
      <Localisation Language="pt-PT" Translation="Bold" />
      <Localisation Language="fr-CH" Translation="Bold" />
      <Localisation Language="de-DE" Translation="Bold" />
      <Localisation Language="ru-RU" Translation="Bold" />
      <Localisation Language="bg-BG" Translation="Bold" />
      <Localisation Language="sv-SE" Translation="Bold" />
    </Resource>
    <Resource Name="FontStyle96" ID="e5a6430a-e735-4c0b-af30-5e863e29511f">
      <Localisation Language="en-GB" Translation="Bold" Default="True" />
      <Localisation Language="tr-TR" Translation="Bold" />
      <Localisation Language="it-IT" Translation="Bold" />
      <Localisation Language="es-ES" Translation="Bold" />
      <Localisation Language="pt-PT" Translation="Bold" />
      <Localisation Language="fr-CH" Translation="Bold" />
      <Localisation Language="de-DE" Translation="Bold" />
      <Localisation Language="ru-RU" Translation="Bold" />
      <Localisation Language="bg-BG" Translation="Bold" />
      <Localisation Language="sv-SE" Translation="Bold" />
    </Resource>
    <Resource Name="FontStyle97" ID="f51fc6ce-1788-4f60-b9f3-3124bb68a28c">
      <Localisation Language="en-GB" Translation="Bold" Default="True" />
      <Localisation Language="tr-TR" Translation="Bold" />
      <Localisation Language="it-IT" Translation="Bold" />
      <Localisation Language="es-ES" Translation="Bold" />
      <Localisation Language="pt-PT" Translation="Bold" />
      <Localisation Language="fr-CH" Translation="Bold" />
      <Localisation Language="de-DE" Translation="Bold" />
      <Localisation Language="ru-RU" Translation="Bold" />
      <Localisation Language="bg-BG" Translation="Bold" />
      <Localisation Language="sv-SE" Translation="Bold" />
    </Resource>
    <Resource Name="FontStyle98" ID="20f946cc-a2d4-409c-94ab-7cfc0af60ce3">
      <Localisation Language="en-GB" Translation="Bold" Default="True" />
      <Localisation Language="tr-TR" Translation="Bold" />
      <Localisation Language="it-IT" Translation="Bold" />
      <Localisation Language="es-ES" Translation="Bold" />
      <Localisation Language="pt-PT" Translation="Bold" />
      <Localisation Language="fr-CH" Translation="Bold" />
      <Localisation Language="de-DE" Translation="Bold" />
      <Localisation Language="ru-RU" Translation="Bold" />
      <Localisation Language="bg-BG" Translation="Bold" />
      <Localisation Language="sv-SE" Translation="Bold" />
    </Resource>
    <Resource Name="FontStyle99" ID="0d9e899f-d93c-4a19-bf67-07427e7c2839">
      <Localisation Language="en-GB" Translation="Bold" Default="True" />
      <Localisation Language="tr-TR" Translation="Bold" />
      <Localisation Language="it-IT" Translation="Bold" />
      <Localisation Language="es-ES" Translation="Bold" />
      <Localisation Language="pt-PT" Translation="Bold" />
      <Localisation Language="fr-CH" Translation="Bold" />
      <Localisation Language="de-DE" Translation="Bold" />
      <Localisation Language="ru-RU" Translation="Bold" />
      <Localisation Language="bg-BG" Translation="Bold" />
      <Localisation Language="sv-SE" Translation="Bold" />
    </Resource>
  </Resources>
</IagResources>