{"PageElementIdentifier":"9c9cfa57-f826-4d36-8d4c-cd322a6ebeec","ResourceKey":"THE.7f07948f-e8f3-4a2d-8a09-c33aef80a617","Type":"THE.S_SelectionRight","Width":130,"Height":70,"Usable":{"Value":"True","Type":"Boolean"},"Selection_Sta":{"Value":"False","Type":"Boolean"},"Commissioning":{"Value":"False","Type":"Boolean"},"Production":{"Value":"False","Type":"Boolean"},"Selection_Cmd":{"PropertyModel":{"Id":"00000000-0000-0000-0000-000000000000","Name":""},"Type":"Boolean"},"IagControls":[{"PageElementIdentifier":"d624d4bf-433c-40ee-a4e2-01c9142c0e9e","ResourceKey":"Omron.StandardShapes.Polygon","Name":"P_Prod_Border","Fill":{"s":{"X":0,"Y":0},"e":{"X":0,"Y":1},"g":{"c":["{\"c\":4284940134,\"o\":0}","{\"c\":4278757896,\"o\":1}"]}},"Stroke":{"s":{"X":0,"Y":0},"e":{"X":0,"Y":1},"g":{"c":["{\"c\":2152986665,\"o\":0}","{\"c\":4278225408,\"o\":1}"]}},"StrokeThickness":2,"Data":{"pg":"F0 M 130,0 L 10,0 L 0,70 L 130,70 Z"},"Width":130,"Height":70,"Animations":[{"PageElementIdentifier":"9ad40130-dd47-4e60-964d-527cfca92df3","ResourceKey":"Omron.StandardAnimations.Visibility","Name":"____Visibility4","Expression":"Production","isDefaultProperty":false}],"isDefaultProperty":false},{"PageElementIdentifier":"d17a00b7-8f00-4e23-8612-b36a07e49fc9","ResourceKey":"Omron.StandardShapes.Polygon","Name":"P_Comm_Border","Fill":{"s":{"X":0,"Y":0},"e":{"X":0,"Y":1},"g":{"c":["{\"c\":4294951524,\"o\":0}","{\"c\":4291391491,\"o\":1}"]}},"Stroke":{"s":{"X":0,"Y":0},"e":{"X":0,"Y":1},"g":{"c":["{\"c\":16777215,\"o\":0}","{\"c\":4290738944,\"o\":1}"]}},"StrokeThickness":2,"Data":{"pg":"F0 M 130,0 L 10,0 L 0,70 L 130,70 Z"},"Width":130,"Height":70,"Animations":[{"PageElementIdentifier":"77c72dcd-e4d5-4c1e-8627-717f7fb97289","ResourceKey":"Omron.StandardAnimations.Visibility","Name":"____Visibility3","Expression":"Commissioning","isDefaultProperty":false}],"isDefaultProperty":false},{"PageElementIdentifier":"faf909d0-2dd4-41d7-bdfa-cd8949809f18","ResourceKey":"Omron.StandardShapes.Polygon","Name":"P_Border","Fill":{"s":{"X":0,"Y":0},"e":{"X":0,"Y":1},"g":{"c":["{\"c\":4283288573,\"o\":0}","{\"c\":4278423497,\"o\":1}"]}},"Stroke":{"s":{"X":0,"Y":0},"e":{"X":0,"Y":1},"g":{"c":["{\"c\":14349823,\"o\":0}","{\"c\":4279014089,\"o\":1}"]}},"StrokeThickness":2,"Data":{"pg":"F0 M 130,0 L 10,0 L 0,70 L 130,70 Z"},"Width":130,"Height":70,"Animations":[{"PageElementIdentifier":"552b6a38-ca9c-40b1-b35f-3be31632a44b","ResourceKey":"Omron.StandardAnimations.Visibility","Name":"____Visibility0","Expression":"Not (Production or Commissioning)","isDefaultProperty":false}],"isDefaultProperty":false},{"PageElementIdentifier":"00cc1f08-bf0a-4174-bbfe-c9a5d6af0b2f","ResourceKey":"Omron.StandardShapes.Polygon","Name":"P_Border_Background","Fill":{"s":{"X":0,"Y":0},"e":{"X":0,"Y":1},"g":{"c":["{\"c\":4288059030,\"o\":0}","{\"c\":4291546059,\"o\":0.102803738317757}","{\"c\":4293651435,\"o\":0.908878504672897}","{\"c\":4287335307,\"o\":1}"]}},"Stroke":{"s":{"X":0,"Y":0},"e":{"X":0,"Y":1},"g":{"c":["{\"c\":4285295983,\"o\":0}","{\"c\":4284703333,\"o\":1}"]}},"StrokeThickness":2,"Data":{"pg":"F0 M 140,0 L 8.46153846153846,0 L 0,70 L 140,70 Z"},"Left":10,"Top":10,"Width":120,"Height":50,"isDefaultProperty":false},{"PageElementIdentifier":"f9ed6ce9-bcc2-4ed1-a191-3a82e0068a17","ResourceKey":"Omron.StandardShapes.Polygon","Name":"P_On","Fill":{"c":2154233702},"Stroke":{"c":4278222848},"StrokeThickness":4,"Data":{"pg":"F0 M 1.24710140880779E-07,50 L 62.2222234540515,50.0000011845056 L 70.0000000187463,0 L 7.77777910232544,1.18450558161953E-06 Z"},"Left":10,"Top":10,"Width":69.999999875289859,"Height":50,"Animations":[{"PageElementIdentifier":"7acc8cc5-d09e-4477-88a0-fc9b937e1c4e","ResourceKey":"Omron.StandardAnimations.Visibility","Name":"____Visibility16","Expression":"Selection_Sta=True","isDefaultProperty":false}],"isDefaultProperty":false},{"PageElementIdentifier":"011f1e79-fa5c-4919-99d2-ff8d8e3ad988","ResourceKey":"Omron.StandardShapes.Polygon","Name":"P_Off","Fill":{"c":2164195328},"Stroke":{"c":4289864226},"StrokeThickness":4,"Data":{"pg":"F0 M 60,0 L 7.77777777777778,0 L 0,50 L 60,50 Z"},"Left":70,"Top":10,"Width":60,"Height":50,"Animations":[{"PageElementIdentifier":"4694683f-394d-48e8-b607-bde1b28207e7","ResourceKey":"Omron.StandardAnimations.Visibility","Name":"____Visibility17","Expression":"Selection_Sta=False","isDefaultProperty":false}],"isDefaultProperty":false},{"PageElementIdentifier":"a8f0bc2a-82f9-4f58-96da-d8a18280e762","ResourceKey":"Omron.StandardControls.Label","Name":"L_On","Text":"623dcf7f-16c4-4e12-9273-73fd14eb353d","FontFamily":"cb047f06-4bb2-43a7-9519-b77f06ab33a8","FontSize":"c7c9d494-8def-492b-bbda-fa26f90d9707","FontStyle":"ba30ba25-9c69-4e32-8cb4-0692b9a70d1e","HorizontalContentAlignment":{"v":"Center"},"VerticalContentAlignment":{"v":"Center"},"NAPadding":{"Left":0,"Top":0,"Right":0,"Bottom":3},"Foreground":{"c":4278190080},"Left":20,"Top":10,"Width":50,"Height":50,"isDefaultProperty":false},{"PageElementIdentifier":"488c98b8-3723-47c6-858b-860276676376","ResourceKey":"Omron.StandardControls.Label","Name":"L_Off","Text":"0642f5d5-e565-48a1-8924-6d028071174d","FontFamily":"cb047f06-4bb2-43a7-9519-b77f06ab33a8","FontSize":"03402e91-ce04-41f8-8ecb-3aa17a37818f","FontStyle":"7ccbcdd1-3730-4537-b9c3-b3a46e868718","HorizontalContentAlignment":{"v":"Center"},"VerticalContentAlignment":{"v":"Center"},"NAPadding":{"Left":0,"Top":0,"Right":0,"Bottom":3},"Foreground":{"c":4278190080},"Left":80,"Top":10,"Width":50,"Height":50,"isDefaultProperty":false},{"PageElementIdentifier":"dc83a807-36af-4ef0-841e-b7dbc675a16d","ResourceKey":"Omron.StandardShapes.Polygon","Name":"P_Action","Fill":{"c":16777215},"Stroke":{"c":16777215},"Data":{"pg":"F0 M 0,70 L 10,0 L 130,0 L 130,70 Z"},"Width":130,"Height":70,"Animations":[{"PageElementIdentifier":"852389a1-a1cd-468b-89ed-c0875c3ba39d","ResourceKey":"Omron.StandardAnimations.Enable","Name":"____Enable1","Expression":"Usable And Not Production","isDefaultProperty":false},{"PageElementIdentifier":"127d1225-5bb3-42c8-916e-a74dafa9bb9f","ResourceKey":"Omron.StandardAnimations.ColorChangeBoolean","Name":"____ColorChangeBoolean0","Expression":"Usable","OffColor":{"ColorContext":null,"A":160,"R":127,"G":127,"B":127,"ScA":0.627451,"ScR":0.212230757,"ScG":0.212230757,"ScB":0.212230757},"OnColor":{"ColorContext":null,"A":0,"R":255,"G":255,"B":255,"ScA":0,"ScR":1,"ScG":1,"ScB":1},"isDefaultProperty":false}],"isDefaultProperty":false},{"PageElementIdentifier":"72e636f8-c0bd-4be6-aca0-b8e1cfab8e3c","ResourceKey":"Omron.ButtonControls.Button","Name":"B_Action","Text":"a8e2a797-6af1-47ed-acb3-f44b3d4cb5a2","FontFamily":"cb047f06-4bb2-43a7-9519-b77f06ab33a8","FontSize":"516fcb08-00c1-4877-8fef-931f94d8f34d","FontStyle":"bc454f76-62bf-4a06-86bd-351238bf56a9","ForegroundNormal":{"c":16777215},"ForegroundPressed":{"c":16777215},"BackgroundNormal":{"c":16777215},"BackgroundPressed":{"c":16777215},"BorderBrushNormal":{"c":16777215},"BorderBrushPressed":{"c":16777215},"Width":130,"Height":70,"Animations":[{"PageElementIdentifier":"18cdd145-5e4d-4dc2-aa30-377611961763","ResourceKey":"Omron.StandardAnimations.Enable","Name":"____Enable0","Expression":"Usable","isDefaultProperty":false},{"PageElementIdentifier":"656398a5-6bd9-4f11-8d92-87f72d3808b9","ResourceKey":"Omron.StandardAnimations.Visibility","Name":"____Visibility2","Expression":"Usable","isDefaultProperty":false}],"Events":[{"PageElementIdentifier":"df5770de-5c26-43f4-b6e5-dfa87fe0d900","ResourceKey":"Omron.StandardEvents.Click","Name":"Click0","Actions":[{"PageElementIdentifier":"3095d989-ee8e-49e4-9b10-aff6189d8272","ResourceKey":"Omron.StandardActions.TriggerEvent","Name":"TriggerEvent1","UserEventName":{"Id":"fb11e59b-0c89-423e-9b6e-748dc986c413","Name":"OnPress"},"isDefaultProperty":false},{"PageElementIdentifier":"6a05bb10-9b92-4b96-9ebc-86585133e06f","ResourceKey":"Omron.StandardActions.InvertVariable","Name":"InvertVariable1","VariableName":{"Id":"3f138171-5a63-4ec8-b57a-74f04a2c25ba","Name":"Selection_Cmd"},"isDefaultProperty":false},{"PageElementIdentifier":"f223adfa-221e-4cba-a3ec-02e0d0786185","ResourceKey":"Omron.StandardActions.TriggerEvent","Name":"TriggerEvent0","UserEventName":{"Id":"6191cb44-88e0-486e-bcbd-4adfe1d8b7e1","Name":"OnRelease"},"isDefaultProperty":false}],"isDefaultProperty":false}],"isDefaultProperty":false}],"serialData":{},"serialCodeData":{},"serialScalingData":{},"isDefaultProperty":false}