<?xml version="1.0" encoding="utf-8"?>
<IagResources>
  <Resources Type="Strings">
    <Resource Name="String60" ID="64ae8ff5-7f49-49aa-82ae-ce4de33773cc">
      <Localisation Language="en-GB" Translation="IN" Default="True" />
      <Localisation Language="tr-TR" Translation="" />
      <Localisation Language="it-IT" Translation="" />
      <Localisation Language="es-ES" Translation="" />
      <Localisation Language="pt-PT" Translation="" />
      <Localisation Language="fr-CH" Translation="" />
      <Localisation Language="de-DE" Translation="" />
      <Localisation Language="ru-RU" Translation="" />
      <Localisation Language="bg-BG" Translation="" />
      <Localisation Language="sv-SE" Translation="" />
    </Resource>
    <Resource Name="String61" ID="31b30efe-f09d-4b7d-98ff-aaf3771da6e8">
      <Localisation Language="en-GB" Translation="OFF" Default="True" />
      <Localisation Language="tr-TR" Translation="" />
      <Localisation Language="it-IT" Translation="" />
      <Localisation Language="es-ES" Translation="" />
      <Localisation Language="pt-PT" Translation="" />
      <Localisation Language="fr-CH" Translation="" />
      <Localisation Language="de-DE" Translation="" />
      <Localisation Language="ru-RU" Translation="" />
      <Localisation Language="bg-BG" Translation="" />
      <Localisation Language="sv-SE" Translation="" />
    </Resource>
    <Resource Name="String62" ID="f3d92982-6213-4e51-a2ee-ef0d952a0f62">
      <Localisation Language="en-GB" Translation="ON" Default="True" />
      <Localisation Language="tr-TR" Translation="" />
      <Localisation Language="it-IT" Translation="" />
      <Localisation Language="es-ES" Translation="" />
      <Localisation Language="pt-PT" Translation="" />
      <Localisation Language="fr-CH" Translation="" />
      <Localisation Language="de-DE" Translation="" />
      <Localisation Language="ru-RU" Translation="" />
      <Localisation Language="bg-BG" Translation="" />
      <Localisation Language="sv-SE" Translation="" />
    </Resource>
    <Resource Name="String63" ID="fc9be7a7-92ad-49cf-9f7d-c48761bf8bdf">
      <Localisation Language="en-GB" Translation="TRANS" Default="True" />
      <Localisation Language="tr-TR" Translation="" />
      <Localisation Language="it-IT" Translation="" />
      <Localisation Language="es-ES" Translation="" />
      <Localisation Language="pt-PT" Translation="" />
      <Localisation Language="fr-CH" Translation="" />
      <Localisation Language="de-DE" Translation="" />
      <Localisation Language="ru-RU" Translation="" />
      <Localisation Language="bg-BG" Translation="" />
      <Localisation Language="sv-SE" Translation="" />
    </Resource>
    <Resource Name="String64" ID="1f0e1de5-bff5-49e2-bf46-8f645a22cc28">
      <Localisation Language="en-GB" Translation="OUT" Default="True" />
      <Localisation Language="tr-TR" Translation="" />
      <Localisation Language="it-IT" Translation="" />
      <Localisation Language="es-ES" Translation="" />
      <Localisation Language="pt-PT" Translation="" />
      <Localisation Language="fr-CH" Translation="" />
      <Localisation Language="de-DE" Translation="" />
      <Localisation Language="ru-RU" Translation="" />
      <Localisation Language="bg-BG" Translation="" />
      <Localisation Language="sv-SE" Translation="" />
    </Resource>
    <Resource Name="String66" ID="4dc4b5ea-e7d0-458c-a309-86f8a7ebd812">
      <Localisation Language="en-GB" Translation="T1" Default="True" />
      <Localisation Language="tr-TR" Translation="" />
      <Localisation Language="it-IT" Translation="" />
      <Localisation Language="es-ES" Translation="" />
      <Localisation Language="pt-PT" Translation="" />
      <Localisation Language="fr-CH" Translation="" />
      <Localisation Language="de-DE" Translation="" />
      <Localisation Language="ru-RU" Translation="" />
      <Localisation Language="bg-BG" Translation="" />
      <Localisation Language="sv-SE" Translation="" />
    </Resource>
    <Resource Name="String67" ID="e80219ff-edf0-4ee0-8c7a-f2a6559d7c8d">
      <Localisation Language="en-GB" Translation="T2" Default="True" />
      <Localisation Language="tr-TR" Translation="" />
      <Localisation Language="it-IT" Translation="" />
      <Localisation Language="es-ES" Translation="" />
      <Localisation Language="pt-PT" Translation="" />
      <Localisation Language="fr-CH" Translation="" />
      <Localisation Language="de-DE" Translation="" />
      <Localisation Language="ru-RU" Translation="" />
      <Localisation Language="bg-BG" Translation="" />
      <Localisation Language="sv-SE" Translation="" />
    </Resource>
    <Resource Name="String69" ID="a509dd2e-8866-45fb-bc69-32a312ca78e3">
      <Localisation Language="en-GB" Translation="T" Default="True" />
      <Localisation Language="tr-TR" Translation="" />
      <Localisation Language="it-IT" Translation="" />
      <Localisation Language="es-ES" Translation="" />
      <Localisation Language="pt-PT" Translation="" />
      <Localisation Language="fr-CH" Translation="" />
      <Localisation Language="de-DE" Translation="" />
      <Localisation Language="ru-RU" Translation="" />
      <Localisation Language="bg-BG" Translation="" />
      <Localisation Language="sv-SE" Translation="" />
    </Resource>
    <Resource Name="THE_A_0" ID="9f759693-8e38-4a01-a38a-0cf16b785fd6">
      <Localisation Language="en-GB" Translation="0" Default="True" />
      <Localisation Language="tr-TR" Translation="" />
      <Localisation Language="it-IT" Translation="" />
      <Localisation Language="es-ES" Translation="" />
      <Localisation Language="pt-PT" Translation="" />
      <Localisation Language="fr-CH" Translation="" />
      <Localisation Language="de-DE" Translation="" />
      <Localisation Language="ru-RU" Translation="" />
      <Localisation Language="bg-BG" Translation="" />
      <Localisation Language="sv-SE" Translation="" />
    </Resource>
    <Resource Name="THE_A_1" ID="4604c7e3-f826-4e01-8253-b954a52198b7">
      <Localisation Language="en-GB" Translation="1" Default="True" />
      <Localisation Language="tr-TR" Translation="" />
      <Localisation Language="it-IT" Translation="" />
      <Localisation Language="es-ES" Translation="" />
      <Localisation Language="pt-PT" Translation="" />
      <Localisation Language="fr-CH" Translation="" />
      <Localisation Language="de-DE" Translation="" />
      <Localisation Language="ru-RU" Translation="" />
      <Localisation Language="bg-BG" Translation="" />
      <Localisation Language="sv-SE" Translation="" />
    </Resource>
  </Resources>
  <Resources Type="FontSizes">
    <Resource Name="FontSize571" ID="c1731562-3777-4a3e-a7fd-fb79a0d3a5d5">
      <Localisation Language="en-GB" Translation="12" Default="True" />
      <Localisation Language="tr-TR" Translation="12" />
      <Localisation Language="it-IT" Translation="12" />
      <Localisation Language="es-ES" Translation="12" />
      <Localisation Language="pt-PT" Translation="12" />
      <Localisation Language="fr-CH" Translation="12" />
      <Localisation Language="de-DE" Translation="12" />
      <Localisation Language="ru-RU" Translation="12" />
      <Localisation Language="bg-BG" Translation="12" />
      <Localisation Language="sv-SE" Translation="12" />
    </Resource>
    <Resource Name="FontSize209" ID="b9f13a89-0cb0-4b7b-a595-a1d86742f89e">
      <Localisation Language="en-GB" Translation="16" Default="True" />
      <Localisation Language="tr-TR" Translation="16" />
      <Localisation Language="it-IT" Translation="16" />
      <Localisation Language="es-ES" Translation="16" />
      <Localisation Language="pt-PT" Translation="16" />
      <Localisation Language="fr-CH" Translation="16" />
      <Localisation Language="de-DE" Translation="16" />
      <Localisation Language="ru-RU" Translation="16" />
      <Localisation Language="bg-BG" Translation="16" />
      <Localisation Language="sv-SE" Translation="12" />
    </Resource>
    <Resource Name="FontSize210" ID="a38f2d92-fa6e-4297-96a8-144a545ab705">
      <Localisation Language="en-GB" Translation="16" Default="True" />
      <Localisation Language="tr-TR" Translation="16" />
      <Localisation Language="it-IT" Translation="16" />
      <Localisation Language="es-ES" Translation="16" />
      <Localisation Language="pt-PT" Translation="16" />
      <Localisation Language="fr-CH" Translation="16" />
      <Localisation Language="de-DE" Translation="16" />
      <Localisation Language="ru-RU" Translation="16" />
      <Localisation Language="bg-BG" Translation="16" />
      <Localisation Language="sv-SE" Translation="12" />
    </Resource>
    <Resource Name="FontSize211" ID="8c1f9d44-bdec-498b-8388-ef80dab3d511">
      <Localisation Language="en-GB" Translation="16" Default="True" />
      <Localisation Language="tr-TR" Translation="16" />
      <Localisation Language="it-IT" Translation="16" />
      <Localisation Language="es-ES" Translation="16" />
      <Localisation Language="pt-PT" Translation="16" />
      <Localisation Language="fr-CH" Translation="16" />
      <Localisation Language="de-DE" Translation="16" />
      <Localisation Language="ru-RU" Translation="16" />
      <Localisation Language="bg-BG" Translation="16" />
      <Localisation Language="sv-SE" Translation="12" />
    </Resource>
    <Resource Name="FontSize212" ID="e6cee5c7-d162-44aa-85e2-e314aeae3385">
      <Localisation Language="en-GB" Translation="16" Default="True" />
      <Localisation Language="tr-TR" Translation="16" />
      <Localisation Language="it-IT" Translation="16" />
      <Localisation Language="es-ES" Translation="16" />
      <Localisation Language="pt-PT" Translation="16" />
      <Localisation Language="fr-CH" Translation="16" />
      <Localisation Language="de-DE" Translation="16" />
      <Localisation Language="ru-RU" Translation="16" />
      <Localisation Language="bg-BG" Translation="16" />
      <Localisation Language="sv-SE" Translation="12" />
    </Resource>
    <Resource Name="FontSize213" ID="15450c9e-37af-432f-86a7-eee2c9ac4e01">
      <Localisation Language="en-GB" Translation="16" Default="True" />
      <Localisation Language="tr-TR" Translation="16" />
      <Localisation Language="it-IT" Translation="16" />
      <Localisation Language="es-ES" Translation="16" />
      <Localisation Language="pt-PT" Translation="16" />
      <Localisation Language="fr-CH" Translation="16" />
      <Localisation Language="de-DE" Translation="16" />
      <Localisation Language="ru-RU" Translation="16" />
      <Localisation Language="bg-BG" Translation="16" />
      <Localisation Language="sv-SE" Translation="12" />
    </Resource>
    <Resource Name="FontSize214" ID="7ce09710-381d-4f17-8cc6-beaffea4dddd">
      <Localisation Language="en-GB" Translation="16" Default="True" />
      <Localisation Language="tr-TR" Translation="16" />
      <Localisation Language="it-IT" Translation="16" />
      <Localisation Language="es-ES" Translation="16" />
      <Localisation Language="pt-PT" Translation="16" />
      <Localisation Language="fr-CH" Translation="16" />
      <Localisation Language="de-DE" Translation="16" />
      <Localisation Language="ru-RU" Translation="16" />
      <Localisation Language="bg-BG" Translation="16" />
      <Localisation Language="sv-SE" Translation="12" />
    </Resource>
    <Resource Name="FontSize215" ID="d34d535f-6eef-475e-bb40-4a180fd19c4b">
      <Localisation Language="en-GB" Translation="20" Default="True" />
      <Localisation Language="tr-TR" Translation="20" />
      <Localisation Language="it-IT" Translation="20" />
      <Localisation Language="es-ES" Translation="20" />
      <Localisation Language="pt-PT" Translation="20" />
      <Localisation Language="fr-CH" Translation="20" />
      <Localisation Language="de-DE" Translation="20" />
      <Localisation Language="ru-RU" Translation="20" />
      <Localisation Language="bg-BG" Translation="20" />
      <Localisation Language="sv-SE" Translation="20" />
    </Resource>
    <Resource Name="FontSize216" ID="ad1316af-5043-4d7d-8b38-d6190ef13b59">
      <Localisation Language="en-GB" Translation="16" Default="True" />
      <Localisation Language="tr-TR" Translation="16" />
      <Localisation Language="it-IT" Translation="16" />
      <Localisation Language="es-ES" Translation="16" />
      <Localisation Language="pt-PT" Translation="16" />
      <Localisation Language="fr-CH" Translation="16" />
      <Localisation Language="de-DE" Translation="16" />
      <Localisation Language="ru-RU" Translation="16" />
      <Localisation Language="bg-BG" Translation="16" />
      <Localisation Language="sv-SE" Translation="12" />
    </Resource>
  </Resources>
  <Resources Type="FontFamilies">
    <Resource Name="FontFamily" ID="a74405cd-aeb9-4ca2-9bae-bfd056ca0350">
      <Localisation Language="en-GB" Translation="Segoe UI" Default="True" />
      <Localisation Language="tr-TR" Translation="Segoe UI" />
      <Localisation Language="it-IT" Translation="Segoe UI" />
      <Localisation Language="es-ES" Translation="Segoe UI" />
      <Localisation Language="pt-PT" Translation="Segoe UI" />
      <Localisation Language="fr-CH" Translation="Segoe UI" />
      <Localisation Language="de-DE" Translation="Segoe UI" />
      <Localisation Language="ru-RU" Translation="Segoe UI" />
      <Localisation Language="bg-BG" Translation="Segoe UI" />
      <Localisation Language="sv-SE" Translation="Segoe UI" />
    </Resource>
  </Resources>
  <Resources Type="FontStyles">
    <Resource Name="FontStyle" ID="ef193659-d61e-44ae-a6b6-bc8f87de2792">
      <Localisation Language="en-GB" Translation="Normal" Default="True" />
      <Localisation Language="tr-TR" Translation="Normal" />
      <Localisation Language="it-IT" Translation="Normal" />
      <Localisation Language="es-ES" Translation="Normal" />
      <Localisation Language="pt-PT" Translation="Normal" />
      <Localisation Language="fr-CH" Translation="Normal" />
      <Localisation Language="de-DE" Translation="Normal" />
      <Localisation Language="ru-RU" Translation="Normal" />
      <Localisation Language="bg-BG" Translation="Normal" />
      <Localisation Language="sv-SE" Translation="Normal" />
    </Resource>
  </Resources>
</IagResources>